user/src/display/LCD/lcd_driver.v
module lcd_driver (
    input          pclk,
    input          rst_n,
    
    input  [15:0]  lcd_id,
    input  [23:0]  pixel_data,
    output [10:0]  pixel_row,
    output [10:0]  pixel_line,
    output [10:0]  o_h_disp,
    output [10:0]  o_v_disp,

    output         lcd_clk,
    output [23:0]  lcd_rgb,
    output         lcd_hs,
    output         lcd_vs,
    output         lcd_de
);

// 4.3' 480*272
parameter  H_SYNC_4342   =  11'd41;     //行同步
parameter  H_BACK_4342   =  11'd2;      //行显示后沿
parameter  H_DISP_4342   =  11'd480;    //行有效数据
parameter  H_FRONT_4342  =  11'd2;      //行显示前沿
parameter  H_TOTAL_4342  =  11'd525;    //行扫描周期

parameter  V_SYNC_4342   =  11'd10;     //场同步
parameter  V_BACK_4342   =  11'd2;      //场显示后沿
parameter  V_DISP_4342   =  11'd272;    //场有效数据
parameter  V_FRONT_4342  =  11'd2;      //场显示前沿
parameter  V_TOTAL_4342  =  11'd286;    //场扫描周期
   
// 7' 800*480   
parameter  H_SYNC_7084   =  11'd128;    //行同步
parameter  H_BACK_7084   =  11'd88;     //行显示后沿
parameter  H_DISP_7084   =  11'd800;    //行有效数据
parameter  H_FRONT_7084  =  11'd40;     //行显示前沿
parameter  H_TOTAL_7084  =  11'd1056;   //行扫描周期
   
parameter  V_SYNC_7084   =  11'd2;      //场同步
parameter  V_BACK_7084   =  11'd33;     //场显示后沿
parameter  V_DISP_7084   =  11'd480;    //场有效数据
parameter  V_FRONT_7084  =  11'd10;     //场显示前沿
parameter  V_TOTAL_7084  =  11'd525;    //场扫描周期       
   
// 7' 1024*600   
parameter  H_SYNC_7016   =  11'd20;     //行同步
parameter  H_BACK_7016   =  11'd140;    //行显示后沿
parameter  H_DISP_7016   =  11'd1024;   //行有效数据
parameter  H_FRONT_7016  =  11'd160;    //行显示前沿
parameter  H_TOTAL_7016  =  11'd1344;   //行扫描周期
   
parameter  V_SYNC_7016   =  11'd3;      //场同步
parameter  V_BACK_7016   =  11'd20;     //场显示后沿
parameter  V_DISP_7016   =  11'd600;    //场有效数据
parameter  V_FRONT_7016  =  11'd12;     //场显示前沿
parameter  V_TOTAL_7016  =  11'd635;    //场扫描周期
   
// 10.1' 1280*800   
parameter  H_SYNC_1018   =  11'd10;     //行同步
parameter  H_BACK_1018   =  11'd80;     //行显示后沿
parameter  H_DISP_1018   =  11'd1280;   //行有效数据
parameter  H_FRONT_1018  =  11'd70;     //行显示前沿
parameter  H_TOTAL_1018  =  11'd1440;   //行扫描周期
   
parameter  V_SYNC_1018   =  11'd3;      //场同步
parameter  V_BACK_1018   =  11'd10;     //场显示后沿
parameter  V_DISP_1018   =  11'd800;    //场有效数据
parameter  V_FRONT_1018  =  11'd10;     //场显示前沿
parameter  V_TOTAL_1018  =  11'd823;    //场扫描周期

// 4.3' 800*480   
parameter  H_SYNC_4384   =  11'd128;    //行同步
parameter  H_BACK_4384   =  11'd88;     //行显示后沿
parameter  H_DISP_4384   =  11'd800;    //行有效数据
parameter  H_FRONT_4384  =  11'd40;     //行显示前沿
parameter  H_TOTAL_4384  =  11'd1056;   //行扫描周期
   
parameter  V_SYNC_4384   =  11'd2;      //场同步
parameter  V_BACK_4384   =  11'd33;     //场显示后沿
parameter  V_DISP_4384   =  11'd480;    //场有效数据
parameter  V_FRONT_4384  =  11'd10;     //场显示前沿
parameter  V_TOTAL_4384  =  11'd525;    //场扫描周期

reg [10:0] h_sync;
reg [10:0] h_back;
reg [10:0] h_disp;
reg [10:0] h_total;
reg [10:0] v_sync;
reg [10:0] v_back;
reg [10:0] v_disp;
reg [10:0] v_total;

assign o_h_disp = h_disp;
assign o_v_disp = v_disp;

//id
always @(posedge pclk) begin
    if(rst_n == 1'b0)begin
        h_sync  <= 11'd0;
        h_back  <= 11'd0;
        h_total <= 11'd0;
        v_sync  <= 11'd0;
        v_back  <= 11'd0;
        v_total <= 11'd0;
    end
    else begin
        case(lcd_id)
            16'h4342:begin
                h_sync  <= H_SYNC_4342;
                h_back  <= H_BACK_4342;
                h_disp  <= H_DISP_4342;
                h_total <= H_TOTAL_4342;
                v_sync  <= V_SYNC_4342;
                v_back  <= V_BACK_4342;
                v_disp  <= V_DISP_4342;
                v_total <= V_TOTAL_4342;
            end
            16'h7084:begin
                h_sync  <= H_SYNC_7084;
                h_back  <= H_BACK_7084;
                h_disp  <= H_DISP_7084;
                h_total <= H_TOTAL_7084;
                v_sync  <= V_SYNC_7084;
                v_back  <= V_BACK_7084;
                v_disp  <= V_DISP_7084;
                v_total <= V_TOTAL_7084;
            end
            16'h7016:begin
                h_sync  <= H_SYNC_7016;
                h_back  <= H_BACK_7016;
                h_disp  <= H_DISP_7016;
                h_total <= H_TOTAL_7016;
                v_sync  <= V_SYNC_7016;
                v_back  <= V_BACK_7016;
                v_disp  <= V_DISP_7016;
                v_total <= V_TOTAL_7016;
            end
            16'h4384:begin
                h_sync  <= H_SYNC_4384;
                h_back  <= H_BACK_4384;
                h_disp  <= H_DISP_4384;
                h_total <= H_TOTAL_4384;
                v_sync  <= V_SYNC_4384;
                v_back  <= V_BACK_4384;
                v_disp  <= V_DISP_4384;
                v_total <= V_TOTAL_4384;
            end
            16'h1018:begin
                h_sync  <= H_SYNC_1018;
                h_back  <= H_BACK_1018;
                h_disp  <= H_DISP_1018;
                h_total <= H_TOTAL_1018;
                v_sync  <= V_SYNC_1018;
                v_back  <= V_BACK_1018;
                v_disp  <= V_DISP_1018;
                v_total <= V_TOTAL_1018;
            end
            default:begin
                h_sync  <= H_SYNC_4342;
                h_back  <= H_BACK_4342;
                h_disp  <= H_DISP_4342;
                h_total <= H_TOTAL_4342;
                v_sync  <= V_SYNC_4342;
                v_back  <= V_BACK_4342;
                v_disp  <= V_DISP_4342;
                v_total <= V_TOTAL_4342;
            end
        endcase
    end
end

//cnt_row
reg [10:0] cnt_row;

always @(posedge pclk) begin
    if(rst_n == 1'b0)begin
        cnt_row <= 11'd0;
    end
    else if(cnt_row == h_total - 1'b1)begin
        cnt_row <= 11'd0;
    end
    else begin
        cnt_row <= cnt_row + 1'b1;
    end
end


//cnt_line
reg [10:0] cnt_line;

always @(posedge pclk) begin
    if(rst_n == 1'b0)begin
        cnt_line <= 11'd0;
    end
    else if((cnt_row == h_total - 1'b1) && (cnt_line == v_total - 1'b1))begin
        cnt_line <= 11'd0;
    end
    else if(cnt_row == h_total - 1'b1)begin
        cnt_line <= cnt_line + 1'b1;
    end
    else begin
        cnt_line <= cnt_line;
    end
end

//lcd_hs
reg r_lcd_hs;

assign lcd_hs = r_lcd_hs;

always @(posedge pclk) begin
    if(rst_n == 1'b0)begin
        r_lcd_hs <= 1'b0;
    end
    else if(cnt_row == h_total - 1'b1)begin
        r_lcd_hs <= 1'b1;
    end
    else if(cnt_row == h_sync - 1'b1)begin
        r_lcd_hs <= 1'b0;
    end
end

//lcd_vs
reg r_lcd_vs;

assign lcd_vs = r_lcd_vs;

always @(posedge pclk) begin
    if(rst_n == 1'b0)begin
        r_lcd_vs <= 1'b0;
    end
    else if((cnt_row == h_total - 1'b1) && (cnt_line == v_total - 1'b1))begin
        r_lcd_vs <= 1'b1;
    end
    else if((cnt_row == h_total - 1'b1) && (cnt_line == v_sync - 1'b1))begin
        r_lcd_vs <= 1'b0;
    end
end

//lcd_de
assign lcd_de  = (cnt_row  >= h_sync + h_back) && 
                 (cnt_row  <= h_sync + h_back + h_disp - 1'b1) && 
                 (cnt_line >= v_sync + v_back) &&
                 (cnt_line <= v_sync + v_back + v_disp - 1'b1);

//pixel_row and pixel_line
wire data_req;

assign data_req = (cnt_row  >= h_sync + h_back - 1'b1) && 
                  (cnt_row  <= h_sync + h_back + h_disp - 1'b1) &&
                  (cnt_line >= v_sync + v_back) &&
                  (cnt_line <= v_sync + v_back + v_disp - 1'b1);

assign pixel_row  = lcd_de ? (cnt_row  - h_sync - h_back) : 11'd0;

reg [10:0] r_pixel_line;

assign pixel_line = r_pixel_line;

always @(posedge pclk) begin
    if(rst_n == 1'b0)begin
        r_pixel_line <= 11'd0;
    end
    else if(data_req)begin
        if(pixel_row == h_disp - 1'b1)begin
            if(pixel_line == v_disp - 1'b1)begin
                r_pixel_line <= 11'd0;
            end
            else begin
                r_pixel_line <= r_pixel_line + 1'b1;
            end
        end
        else begin
            r_pixel_line <= cnt_line - v_sync - v_back;
        end
    end
    else begin
        r_pixel_line <= r_pixel_line;
    end
end

//lcd_clk
assign lcd_clk = pclk;

//lcd_rgb
assign lcd_rgb = lcd_de ? pixel_data : 24'd0;

endmodule

user/sim/LCD/driver_tb.v
module driver_tb();

parameter MAIN_FRE   = 100; //unit MHz
reg                   sys_clk = 0;
reg                   sys_rst = 0;

always begin
    #(500/MAIN_FRE) sys_clk = ~sys_clk;
end

always begin
    #50 sys_rst = 1;
end

//Instance 
// outports wire
wire [10:0] 	pixel_row;
wire [10:0] 	pixel_line;
wire        	lcd_clk;
wire [23:0] 	lcd_rgb;
wire        	lcd_hs;
wire        	lcd_vs;
wire        	lcd_de;

lcd_driver u_lcd_driver(
	.pclk       	( sys_clk     ),
	.rst_n      	( sys_rst     ),
	
    .lcd_id     	( 16'h4342    ),
	.pixel_data 	( {13'd0,pixel_row}   ),
	.pixel_row  	( pixel_row   ),
	.pixel_line 	( pixel_line  ),
	
    .lcd_clk    	( lcd_clk     ),
	.lcd_rgb    	( lcd_rgb     ),
	.lcd_hs     	( lcd_hs      ),
	.lcd_vs     	( lcd_vs      ),
	.lcd_de     	( lcd_de      )
);

initial begin
	$dumpfile("wave.vcd");
	$dumpvars(0,driver_tb);
	#50000 $finish;
end


endmodule  //TOP

user/sim/LCD/wave.vcd
$date
	Wed Nov 15 09:57:40 2023
$end
$version
	Icarus Verilog
$end
$timescale
	1s
$end
$scope module driver_tb $end
$var wire 11 ! pixel_row [10:0] $end
$var wire 11 " pixel_line [10:0] $end
$var wire 1 # lcd_vs $end
$var wire 24 $ lcd_rgb [23:0] $end
$var wire 1 % lcd_hs $end
$var wire 1 & lcd_de $end
$var wire 1 ' lcd_clk $end
$var reg 1 ( sys_clk $end
$var reg 1 ) sys_rst $end
$scope module u_lcd_driver $end
$var wire 1 * data_req $end
$var wire 1 ' lcd_clk $end
$var wire 1 & lcd_de $end
$var wire 1 % lcd_hs $end
$var wire 16 + lcd_id [15:0] $end
$var wire 1 # lcd_vs $end
$var wire 11 , o_h_disp [10:0] $end
$var wire 11 - o_v_disp [10:0] $end
$var wire 1 ( pclk $end
$var wire 24 . pixel_data [23:0] $end
$var wire 11 / pixel_line [10:0] $end
$var wire 1 ) rst_n $end
$var wire 11 0 pixel_row [10:0] $end
$var wire 24 1 lcd_rgb [23:0] $end
$var reg 11 2 cnt_line [10:0] $end
$var reg 11 3 cnt_row [10:0] $end
$var reg 11 4 h_back [10:0] $end
$var reg 11 5 h_disp [10:0] $end
$var reg 11 6 h_sync [10:0] $end
$var reg 11 7 h_total [10:0] $end
$var reg 1 8 r_lcd_hs $end
$var reg 1 9 r_lcd_vs $end
$var reg 11 : r_pixel_line [10:0] $end
$var reg 11 ; v_back [10:0] $end
$var reg 11 < v_disp [10:0] $end
$var reg 11 = v_sync [10:0] $end
$var reg 11 > v_total [10:0] $end
$upscope $end
$upscope $end
$enddefinitions $end
#0
$dumpvars
bx >
bx =
bx <
bx ;
bx :
x9
x8
bx 7
bx 6
bx 5
bx 4
bx 3
bx 2
b0xxxxxxxxxxx 1
bx 0
bx /
b0xxxxxxxxxxx .
bx -
bx ,
b100001101000010 +
x*
0)
0(
0'
x&
x%
b0xxxxxxxxxxx $
x#
bx "
bx !
$end
#5
0*
b0 $
b0 1
b0 .
b0 !
b0 0
b0 >
b0 ;
b0 =
b0 7
b0 4
b0 6
b0 3
b0 2
0%
08
0#
09
b0 "
b0 /
b0 :
1'
1(
#10
0'
0(
#15
1'
1(
#20
0'
0(
#25
1'
1(
#30
0'
0(
#35
1'
1(
#40
0'
0(
#45
1'
1(
#50
0'
0(
1)
#55
0&
b0 .
b0 !
b0 0
b1 3
b100011110 >
b100010000 -
b100010000 <
b10 ;
b1010 =
b1000001101 7
b111100000 ,
b111100000 5
b10 4
b101001 6
1'
1(
#60
0'
0(
#65
b10 3
1'
1(
#70
0'
0(
#75
b11 3
1'
1(
#80
0'
0(
#85
b100 3
1'
1(
#90
0'
0(
#95
b101 3
1'
1(
#100
0'
0(
#105
b110 3
1'
1(
#110
0'
0(
#115
b111 3
1'
1(
#120
0'
0(
#125
b1000 3
1'
1(
#130
0'
0(
#135
b1001 3
1'
1(
#140
0'
0(
#145
b1010 3
1'
1(
#150
0'
0(
#155
b1011 3
1'
1(
#160
0'
0(
#165
b1100 3
1'
1(
#170
0'
0(
#175
b1101 3
1'
1(
#180
0'
0(
#185
b1110 3
1'
1(
#190
0'
0(
#195
b1111 3
1'
1(
#200
0'
0(
#205
b10000 3
1'
1(
#210
0'
0(
#215
b10001 3
1'
1(
#220
0'
0(
#225
b10010 3
1'
1(
#230
0'
0(
#235
b10011 3
1'
1(
#240
0'
0(
#245
b10100 3
1'
1(
#250
0'
0(
#255
b10101 3
1'
1(
#260
0'
0(
#265
b10110 3
1'
1(
#270
0'
0(
#275
b10111 3
1'
1(
#280
0'
0(
#285
b11000 3
1'
1(
#290
0'
0(
#295
b11001 3
1'
1(
#300
0'
0(
#305
b11010 3
1'
1(
#310
0'
0(
#315
b11011 3
1'
1(
#320
0'
0(
#325
b11100 3
1'
1(
#330
0'
0(
#335
b11101 3
1'
1(
#340
0'
0(
#345
b11110 3
1'
1(
#350
0'
0(
#355
b11111 3
1'
1(
#360
0'
0(
#365
b100000 3
1'
1(
#370
0'
0(
#375
b100001 3
1'
1(
#380
0'
0(
#385
b100010 3
1'
1(
#390
0'
0(
#395
b100011 3
1'
1(
#400
0'
0(
#405
b100100 3
1'
1(
#410
0'
0(
#415
b100101 3
1'
1(
#420
0'
0(
#425
b100110 3
1'
1(
#430
0'
0(
#435
b100111 3
1'
1(
#440
0'
0(
#445
b101000 3
1'
1(
#450
0'
0(
#455
b101001 3
1'
1(
#460
0'
0(
#465
b101010 3
1'
1(
#470
0'
0(
#475
b101011 3
1'
1(
#480
0'
0(
#485
b101100 3
1'
1(
#490
0'
0(
#495
b101101 3
1'
1(
#500
0'
0(
#505
b101110 3
1'
1(
#510
0'
0(
#515
b101111 3
1'
1(
#520
0'
0(
#525
b110000 3
1'
1(
#530
0'
0(
#535
b110001 3
1'
1(
#540
0'
0(
#545
b110010 3
1'
1(
#550
0'
0(
#555
b110011 3
1'
1(
#560
0'
0(
#565
b110100 3
1'
1(
#570
0'
0(
#575
b110101 3
1'
1(
#580
0'
0(
#585
b110110 3
1'
1(
#590
0'
0(
#595
b110111 3
1'
1(
#600
0'
0(
#605
b111000 3
1'
1(
#610
0'
0(
#615
b111001 3
1'
1(
#620
0'
0(
#625
b111010 3
1'
1(
#630
0'
0(
#635
b111011 3
1'
1(
#640
0'
0(
#645
b111100 3
1'
1(
#650
0'
0(
#655
b111101 3
1'
1(
#660
0'
0(
#665
b111110 3
1'
1(
#670
0'
0(
#675
b111111 3
1'
1(
#680
0'
0(
#685
b1000000 3
1'
1(
#690
0'
0(
#695
b1000001 3
1'
1(
#700
0'
0(
#705
b1000010 3
1'
1(
#710
0'
0(
#715
b1000011 3
1'
1(
#720
0'
0(
#725
b1000100 3
1'
1(
#730
0'
0(
#735
b1000101 3
1'
1(
#740
0'
0(
#745
b1000110 3
1'
1(
#750
0'
0(
#755
b1000111 3
1'
1(
#760
0'
0(
#765
b1001000 3
1'
1(
#770
0'
0(
#775
b1001001 3
1'
1(
#780
0'
0(
#785
b1001010 3
1'
1(
#790
0'
0(
#795
b1001011 3
1'
1(
#800
0'
0(
#805
b1001100 3
1'
1(
#810
0'
0(
#815
b1001101 3
1'
1(
#820
0'
0(
#825
b1001110 3
1'
1(
#830
0'
0(
#835
b1001111 3
1'
1(
#840
0'
0(
#845
b1010000 3
1'
1(
#850
0'
0(
#855
b1010001 3
1'
1(
#860
0'
0(
#865
b1010010 3
1'
1(
#870
0'
0(
#875
b1010011 3
1'
1(
#880
0'
0(
#885
b1010100 3
1'
1(
#890
0'
0(
#895
b1010101 3
1'
1(
#900
0'
0(
#905
b1010110 3
1'
1(
#910
0'
0(
#915
b1010111 3
1'
1(
#920
0'
0(
#925
b1011000 3
1'
1(
#930
0'
0(
#935
b1011001 3
1'
1(
#940
0'
0(
#945
b1011010 3
1'
1(
#950
0'
0(
#955
b1011011 3
1'
1(
#960
0'
0(
#965
b1011100 3
1'
1(
#970
0'
0(
#975
b1011101 3
1'
1(
#980
0'
0(
#985
b1011110 3
1'
1(
#990
0'
0(
#995
b1011111 3
1'
1(
#1000
0'
0(
#1005
b1100000 3
1'
1(
#1010
0'
0(
#1015
b1100001 3
1'
1(
#1020
0'
0(
#1025
b1100010 3
1'
1(
#1030
0'
0(
#1035
b1100011 3
1'
1(
#1040
0'
0(
#1045
b1100100 3
1'
1(
#1050
0'
0(
#1055
b1100101 3
1'
1(
#1060
0'
0(
#1065
b1100110 3
1'
1(
#1070
0'
0(
#1075
b1100111 3
1'
1(
#1080
0'
0(
#1085
b1101000 3
1'
1(
#1090
0'
0(
#1095
b1101001 3
1'
1(
#1100
0'
0(
#1105
b1101010 3
1'
1(
#1110
0'
0(
#1115
b1101011 3
1'
1(
#1120
0'
0(
#1125
b1101100 3
1'
1(
#1130
0'
0(
#1135
b1101101 3
1'
1(
#1140
0'
0(
#1145
b1101110 3
1'
1(
#1150
0'
0(
#1155
b1101111 3
1'
1(
#1160
0'
0(
#1165
b1110000 3
1'
1(
#1170
0'
0(
#1175
b1110001 3
1'
1(
#1180
0'
0(
#1185
b1110010 3
1'
1(
#1190
0'
0(
#1195
b1110011 3
1'
1(
#1200
0'
0(
#1205
b1110100 3
1'
1(
#1210
0'
0(
#1215
b1110101 3
1'
1(
#1220
0'
0(
#1225
b1110110 3
1'
1(
#1230
0'
0(
#1235
b1110111 3
1'
1(
#1240
0'
0(
#1245
b1111000 3
1'
1(
#1250
0'
0(
#1255
b1111001 3
1'
1(
#1260
0'
0(
#1265
b1111010 3
1'
1(
#1270
0'
0(
#1275
b1111011 3
1'
1(
#1280
0'
0(
#1285
b1111100 3
1'
1(
#1290
0'
0(
#1295
b1111101 3
1'
1(
#1300
0'
0(
#1305
b1111110 3
1'
1(
#1310
0'
0(
#1315
b1111111 3
1'
1(
#1320
0'
0(
#1325
b10000000 3
1'
1(
#1330
0'
0(
#1335
b10000001 3
1'
1(
#1340
0'
0(
#1345
b10000010 3
1'
1(
#1350
0'
0(
#1355
b10000011 3
1'
1(
#1360
0'
0(
#1365
b10000100 3
1'
1(
#1370
0'
0(
#1375
b10000101 3
1'
1(
#1380
0'
0(
#1385
b10000110 3
1'
1(
#1390
0'
0(
#1395
b10000111 3
1'
1(
#1400
0'
0(
#1405
b10001000 3
1'
1(
#1410
0'
0(
#1415
b10001001 3
1'
1(
#1420
0'
0(
#1425
b10001010 3
1'
1(
#1430
0'
0(
#1435
b10001011 3
1'
1(
#1440
0'
0(
#1445
b10001100 3
1'
1(
#1450
0'
0(
#1455
b10001101 3
1'
1(
#1460
0'
0(
#1465
b10001110 3
1'
1(
#1470
0'
0(
#1475
b10001111 3
1'
1(
#1480
0'
0(
#1485
b10010000 3
1'
1(
#1490
0'
0(
#1495
b10010001 3
1'
1(
#1500
0'
0(
#1505
b10010010 3
1'
1(
#1510
0'
0(
#1515
b10010011 3
1'
1(
#1520
0'
0(
#1525
b10010100 3
1'
1(
#1530
0'
0(
#1535
b10010101 3
1'
1(
#1540
0'
0(
#1545
b10010110 3
1'
1(
#1550
0'
0(
#1555
b10010111 3
1'
1(
#1560
0'
0(
#1565
b10011000 3
1'
1(
#1570
0'
0(
#1575
b10011001 3
1'
1(
#1580
0'
0(
#1585
b10011010 3
1'
1(
#1590
0'
0(
#1595
b10011011 3
1'
1(
#1600
0'
0(
#1605
b10011100 3
1'
1(
#1610
0'
0(
#1615
b10011101 3
1'
1(
#1620
0'
0(
#1625
b10011110 3
1'
1(
#1630
0'
0(
#1635
b10011111 3
1'
1(
#1640
0'
0(
#1645
b10100000 3
1'
1(
#1650
0'
0(
#1655
b10100001 3
1'
1(
#1660
0'
0(
#1665
b10100010 3
1'
1(
#1670
0'
0(
#1675
b10100011 3
1'
1(
#1680
0'
0(
#1685
b10100100 3
1'
1(
#1690
0'
0(
#1695
b10100101 3
1'
1(
#1700
0'
0(
#1705
b10100110 3
1'
1(
#1710
0'
0(
#1715
b10100111 3
1'
1(
#1720
0'
0(
#1725
b10101000 3
1'
1(
#1730
0'
0(
#1735
b10101001 3
1'
1(
#1740
0'
0(
#1745
b10101010 3
1'
1(
#1750
0'
0(
#1755
b10101011 3
1'
1(
#1760
0'
0(
#1765
b10101100 3
1'
1(
#1770
0'
0(
#1775
b10101101 3
1'
1(
#1780
0'
0(
#1785
b10101110 3
1'
1(
#1790
0'
0(
#1795
b10101111 3
1'
1(
#1800
0'
0(
#1805
b10110000 3
1'
1(
#1810
0'
0(
#1815
b10110001 3
1'
1(
#1820
0'
0(
#1825
b10110010 3
1'
1(
#1830
0'
0(
#1835
b10110011 3
1'
1(
#1840
0'
0(
#1845
b10110100 3
1'
1(
#1850
0'
0(
#1855
b10110101 3
1'
1(
#1860
0'
0(
#1865
b10110110 3
1'
1(
#1870
0'
0(
#1875
b10110111 3
1'
1(
#1880
0'
0(
#1885
b10111000 3
1'
1(
#1890
0'
0(
#1895
b10111001 3
1'
1(
#1900
0'
0(
#1905
b10111010 3
1'
1(
#1910
0'
0(
#1915
b10111011 3
1'
1(
#1920
0'
0(
#1925
b10111100 3
1'
1(
#1930
0'
0(
#1935
b10111101 3
1'
1(
#1940
0'
0(
#1945
b10111110 3
1'
1(
#1950
0'
0(
#1955
b10111111 3
1'
1(
#1960
0'
0(
#1965
b11000000 3
1'
1(
#1970
0'
0(
#1975
b11000001 3
1'
1(
#1980
0'
0(
#1985
b11000010 3
1'
1(
#1990
0'
0(
#1995
b11000011 3
1'
1(
#2000
0'
0(
#2005
b11000100 3
1'
1(
#2010
0'
0(
#2015
b11000101 3
1'
1(
#2020
0'
0(
#2025
b11000110 3
1'
1(
#2030
0'
0(
#2035
b11000111 3
1'
1(
#2040
0'
0(
#2045
b11001000 3
1'
1(
#2050
0'
0(
#2055
b11001001 3
1'
1(
#2060
0'
0(
#2065
b11001010 3
1'
1(
#2070
0'
0(
#2075
b11001011 3
1'
1(
#2080
0'
0(
#2085
b11001100 3
1'
1(
#2090
0'
0(
#2095
b11001101 3
1'
1(
#2100
0'
0(
#2105
b11001110 3
1'
1(
#2110
0'
0(
#2115
b11001111 3
1'
1(
#2120
0'
0(
#2125
b11010000 3
1'
1(
#2130
0'
0(
#2135
b11010001 3
1'
1(
#2140
0'
0(
#2145
b11010010 3
1'
1(
#2150
0'
0(
#2155
b11010011 3
1'
1(
#2160
0'
0(
#2165
b11010100 3
1'
1(
#2170
0'
0(
#2175
b11010101 3
1'
1(
#2180
0'
0(
#2185
b11010110 3
1'
1(
#2190
0'
0(
#2195
b11010111 3
1'
1(
#2200
0'
0(
#2205
b11011000 3
1'
1(
#2210
0'
0(
#2215
b11011001 3
1'
1(
#2220
0'
0(
#2225
b11011010 3
1'
1(
#2230
0'
0(
#2235
b11011011 3
1'
1(
#2240
0'
0(
#2245
b11011100 3
1'
1(
#2250
0'
0(
#2255
b11011101 3
1'
1(
#2260
0'
0(
#2265
b11011110 3
1'
1(
#2270
0'
0(
#2275
b11011111 3
1'
1(
#2280
0'
0(
#2285
b11100000 3
1'
1(
#2290
0'
0(
#2295
b11100001 3
1'
1(
#2300
0'
0(
#2305
b11100010 3
1'
1(
#2310
0'
0(
#2315
b11100011 3
1'
1(
#2320
0'
0(
#2325
b11100100 3
1'
1(
#2330
0'
0(
#2335
b11100101 3
1'
1(
#2340
0'
0(
#2345
b11100110 3
1'
1(
#2350
0'
0(
#2355
b11100111 3
1'
1(
#2360
0'
0(
#2365
b11101000 3
1'
1(
#2370
0'
0(
#2375
b11101001 3
1'
1(
#2380
0'
0(
#2385
b11101010 3
1'
1(
#2390
0'
0(
#2395
b11101011 3
1'
1(
#2400
0'
0(
#2405
b11101100 3
1'
1(
#2410
0'
0(
#2415
b11101101 3
1'
1(
#2420
0'
0(
#2425
b11101110 3
1'
1(
#2430
0'
0(
#2435
b11101111 3
1'
1(
#2440
0'
0(
#2445
b11110000 3
1'
1(
#2450
0'
0(
#2455
b11110001 3
1'
1(
#2460
0'
0(
#2465
b11110010 3
1'
1(
#2470
0'
0(
#2475
b11110011 3
1'
1(
#2480
0'
0(
#2485
b11110100 3
1'
1(
#2490
0'
0(
#2495
b11110101 3
1'
1(
#2500
0'
0(
#2505
b11110110 3
1'
1(
#2510
0'
0(
#2515
b11110111 3
1'
1(
#2520
0'
0(
#2525
b11111000 3
1'
1(
#2530
0'
0(
#2535
b11111001 3
1'
1(
#2540
0'
0(
#2545
b11111010 3
1'
1(
#2550
0'
0(
#2555
b11111011 3
1'
1(
#2560
0'
0(
#2565
b11111100 3
1'
1(
#2570
0'
0(
#2575
b11111101 3
1'
1(
#2580
0'
0(
#2585
b11111110 3
1'
1(
#2590
0'
0(
#2595
b11111111 3
1'
1(
#2600
0'
0(
#2605
b100000000 3
1'
1(
#2610
0'
0(
#2615
b100000001 3
1'
1(
#2620
0'
0(
#2625
b100000010 3
1'
1(
#2630
0'
0(
#2635
b100000011 3
1'
1(
#2640
0'
0(
#2645
b100000100 3
1'
1(
#2650
0'
0(
#2655
b100000101 3
1'
1(
#2660
0'
0(
#2665
b100000110 3
1'
1(
#2670
0'
0(
#2675
b100000111 3
1'
1(
#2680
0'
0(
#2685
b100001000 3
1'
1(
#2690
0'
0(
#2695
b100001001 3
1'
1(
#2700
0'
0(
#2705
b100001010 3
1'
1(
#2710
0'
0(
#2715
b100001011 3
1'
1(
#2720
0'
0(
#2725
b100001100 3
1'
1(
#2730
0'
0(
#2735
b100001101 3
1'
1(
#2740
0'
0(
#2745
b100001110 3
1'
1(
#2750
0'
0(
#2755
b100001111 3
1'
1(
#2760
0'
0(
#2765
b100010000 3
1'
1(
#2770
0'
0(
#2775
b100010001 3
1'
1(
#2780
0'
0(
#2785
b100010010 3
1'
1(
#2790
0'
0(
#2795
b100010011 3
1'
1(
#2800
0'
0(
#2805
b100010100 3
1'
1(
#2810
0'
0(
#2815
b100010101 3
1'
1(
#2820
0'
0(
#2825
b100010110 3
1'
1(
#2830
0'
0(
#2835
b100010111 3
1'
1(
#2840
0'
0(
#2845
b100011000 3
1'
1(
#2850
0'
0(
#2855
b100011001 3
1'
1(
#2860
0'
0(
#2865
b100011010 3
1'
1(
#2870
0'
0(
#2875
b100011011 3
1'
1(
#2880
0'
0(
#2885
b100011100 3
1'
1(
#2890
0'
0(
#2895
b100011101 3
1'
1(
#2900
0'
0(
#2905
b100011110 3
1'
1(
#2910
0'
0(
#2915
b100011111 3
1'
1(
#2920
0'
0(
#2925
b100100000 3
1'
1(
#2930
0'
0(
#2935
b100100001 3
1'
1(
#2940
0'
0(
#2945
b100100010 3
1'
1(
#2950
0'
0(
#2955
b100100011 3
1'
1(
#2960
0'
0(
#2965
b100100100 3
1'
1(
#2970
0'
0(
#2975
b100100101 3
1'
1(
#2980
0'
0(
#2985
b100100110 3
1'
1(
#2990
0'
0(
#2995
b100100111 3
1'
1(
#3000
0'
0(
#3005
b100101000 3
1'
1(
#3010
0'
0(
#3015
b100101001 3
1'
1(
#3020
0'
0(
#3025
b100101010 3
1'
1(
#3030
0'
0(
#3035
b100101011 3
1'
1(
#3040
0'
0(
#3045
b100101100 3
1'
1(
#3050
0'
0(
#3055
b100101101 3
1'
1(
#3060
0'
0(
#3065
b100101110 3
1'
1(
#3070
0'
0(
#3075
b100101111 3
1'
1(
#3080
0'
0(
#3085
b100110000 3
1'
1(
#3090
0'
0(
#3095
b100110001 3
1'
1(
#3100
0'
0(
#3105
b100110010 3
1'
1(
#3110
0'
0(
#3115
b100110011 3
1'
1(
#3120
0'
0(
#3125
b100110100 3
1'
1(
#3130
0'
0(
#3135
b100110101 3
1'
1(
#3140
0'
0(
#3145
b100110110 3
1'
1(
#3150
0'
0(
#3155
b100110111 3
1'
1(
#3160
0'
0(
#3165
b100111000 3
1'
1(
#3170
0'
0(
#3175
b100111001 3
1'
1(
#3180
0'
0(
#3185
b100111010 3
1'
1(
#3190
0'
0(
#3195
b100111011 3
1'
1(
#3200
0'
0(
#3205
b100111100 3
1'
1(
#3210
0'
0(
#3215
b100111101 3
1'
1(
#3220
0'
0(
#3225
b100111110 3
1'
1(
#3230
0'
0(
#3235
b100111111 3
1'
1(
#3240
0'
0(
#3245
b101000000 3
1'
1(
#3250
0'
0(
#3255
b101000001 3
1'
1(
#3260
0'
0(
#3265
b101000010 3
1'
1(
#3270
0'
0(
#3275
b101000011 3
1'
1(
#3280
0'
0(
#3285
b101000100 3
1'
1(
#3290
0'
0(
#3295
b101000101 3
1'
1(
#3300
0'
0(
#3305
b101000110 3
1'
1(
#3310
0'
0(
#3315
b101000111 3
1'
1(
#3320
0'
0(
#3325
b101001000 3
1'
1(
#3330
0'
0(
#3335
b101001001 3
1'
1(
#3340
0'
0(
#3345
b101001010 3
1'
1(
#3350
0'
0(
#3355
b101001011 3
1'
1(
#3360
0'
0(
#3365
b101001100 3
1'
1(
#3370
0'
0(
#3375
b101001101 3
1'
1(
#3380
0'
0(
#3385
b101001110 3
1'
1(
#3390
0'
0(
#3395
b101001111 3
1'
1(
#3400
0'
0(
#3405
b101010000 3
1'
1(
#3410
0'
0(
#3415
b101010001 3
1'
1(
#3420
0'
0(
#3425
b101010010 3
1'
1(
#3430
0'
0(
