user/src/Base/FIFO/syn_fifo.v
module syn_fifo #(
    parameter DATA_WIDTH = 16,
    parameter DEPTH      = 128
) (
    input                            sys_clk,
    input                            sys_rst,

    input                            wr_en,
    input   [DATA_WIDTH - 1 : 0]     wr_data,

    input                            rd_en,
    output  reg [DATA_WIDTH - 1 : 0] rd_data,

    output                           full,
    output                           empty
    
);

localparam ADDR_WIDTH = $clog2(DEPTH);

reg [DATA_WIDTH - 1 : 0] mem[DEPTH - 1 : 0];

reg [ADDR_WIDTH - 1 : 0] wr_addr,rd_addr;

//wr_addr
always @(posedge sys_clk) begin
    if(sys_rst == 1'b0)
        wr_addr <= {(ADDR_WIDTH){1'b0}};
    else begin
        if(wr_addr == DEPTH - 1'b1)
            wr_addr <= {(ADDR_WIDTH){1'b0}};
        else if(wr_en && (!full))
            wr_addr <= wr_addr + 1'b1;
    end
end

//rd_addr
always @(posedge sys_clk) begin
    if(sys_rst == 1'b0)
        rd_addr <= {(ADDR_WIDTH){1'b0}};
    else begin
        if(rd_addr == DEPTH - 1'b1)
            rd_addr <= {(ADDR_WIDTH){1'b0}};
        else if(rd_en && (!empty))
            rd_addr <= rd_addr + 1'b1;
    end
end

//full and empty
reg [ADDR_WIDTH - 1 : 0] data_cnt;

assign full  = (data_cnt == DEPTH - 1'b1)         ? 1'b1 : 1'b0;
assign empty = (data_cnt == {(ADDR_WIDTH){1'b0}}) ? 1'b1 : 1'b0;

always @(posedge sys_clk) begin
    if(sys_rst == 1'b0)
        data_cnt <= {(ADDR_WIDTH){1'b0}};
    else if(wr_en && rd_en && (!full) && (!empty))begin
        data_cnt <= data_cnt;
    end
    else if(wr_en && (!full))begin
        data_cnt <= data_cnt + 1'b1;
    end
    else if(rd_en && (!empty))begin
        data_cnt <= data_cnt - 1'b1;
    end
end

//write
integer index;

always @(posedge sys_clk) begin
    if(sys_rst == 1'b0)begin
        for(index = 0; index < DEPTH; index = index + 1)begin
            mem[index] <= {(ADDR_WIDTH){1'b0}};
        end
    end
    else if(wr_en && !full)
        mem[wr_addr] <= wr_data;
end

//read
always @(*) begin
    //if(rd_en && !empty)
    rd_data <= mem[rd_addr];
    //else 
        //rd_data <= {(ADDR_WIDTH){1'bz}};
end

endmodule

user/sim/Base/FIFO/syn_fifo_tb.v
module syn_fifo_tb();

parameter DATA_WIDTH = 16;
parameter DEPTH      = 128;
parameter MAIN_FRE   = 100; //unit MHz
reg                   sys_clk = 0;
reg                   sys_rst = 0;

always begin
    #(500/MAIN_FRE) sys_clk = ~sys_clk;
end

always begin
    #50 sys_rst = 1;
end

//Instance 
// outports wire
wire [DATA_WIDTH-1:0] 	rd_data;
wire                  	full;
wire                  	empty;

reg                     wr_en;
reg  [DATA_WIDTH-1:0]   wr_data;
reg                     rd_en;

always @(posedge sys_clk) begin
    if(sys_rst == 1'b0)
        wr_en <= 1'b1;
    else if(full)
        wr_en <= 1'b0;
end

always @(posedge sys_clk) begin
    if(sys_rst == 1'b0)
        wr_data <= 16'd2;
    else if(wr_en)
        wr_data <= wr_data + 1'b1;
end

always @(posedge sys_clk) begin
    if(sys_rst == 1'b0)
        rd_en <= 1'b0;
    else if(full)
        rd_en <= 1'b1;
end

syn_fifo #(
    .DATA_WIDTH (16),
    .DEPTH      (125)
)
u_syn_fifo(
    .sys_clk 	( sys_clk  ),
    .sys_rst 	( sys_rst  ),
    .wr_en   	( wr_en    ),
    .wr_data 	( wr_data  ),
    .rd_en   	( rd_en    ),
    .rd_data 	( rd_data  ),
    .full    	( full     ),
    .empty   	( empty    )
);

initial begin            
    $dumpfile("wave.vcd");        
    $dumpvars(0, syn_fifo_tb);    
    #50000 $finish;
end

endmodule  //TOP

user/sim/Base/FIFO/wave.vcd
$date
	Thu Nov 16 23:58:33 2023
$end
$version
	Icarus Verilog
$end
$timescale
	1s
$end
$scope module syn_fifo_tb $end
$var wire 16 ! rd_data [15:0] $end
$var wire 1 " full $end
$var wire 1 # empty $end
$var reg 1 $ rd_en $end
$var reg 1 % sys_clk $end
$var reg 1 & sys_rst $end
$var reg 16 ' wr_data [15:0] $end
$var reg 1 ( wr_en $end
$scope module u_syn_fifo $end
$var wire 1 $ rd_en $end
$var wire 1 % sys_clk $end
$var wire 1 & sys_rst $end
$var wire 16 ) wr_data [15:0] $end
$var wire 1 ( wr_en $end
$var reg 7 * data_cnt [6:0] $end
$var reg 1 # empty $end
$var reg 1 " full $end
$var reg 7 + rd_addr [6:0] $end
$var reg 16 , rd_data [15:0] $end
$var reg 7 - wr_addr [6:0] $end
$var integer 32 . index [31:0] $end
$upscope $end
$upscope $end
$enddefinitions $end
#0
$dumpvars
bx .
bx -
bx ,
bx +
bx *
bx )
x(
bx '
0&
0%
x$
x#
x"
bx !
$end
#5
b0 -
b0 +
0"
0#
b0 *
b0zzzzzzz !
b0zzzzzzz ,
1(
b10 '
b10 )
0$
b1111101 .
1%
#10
0%
#15
b1111101 .
1%
#20
0%
#25
b1111101 .
1%
#30
0%
#35
b1111101 .
1%
#40
0%
#45
b1111101 .
1%
#50
0%
1&
#55
b11 '
b11 )
b1 *
1#
b1 -
1%
#60
0%
#65
b10 -
0#
b10 *
b100 '
b100 )
1%
#70
0%
#75
b101 '
b101 )
b11 *
b11 -
1%
#80
0%
#85
b100 -
b100 *
b110 '
b110 )
1%
#90
0%
#95
b111 '
b111 )
b101 *
b101 -
1%
#100
0%
#105
b110 -
b110 *
b1000 '
b1000 )
1%
#110
0%
#115
b1001 '
b1001 )
b111 *
b111 -
1%
#120
0%
#125
b1000 -
b1000 *
b1010 '
b1010 )
1%
#130
0%
#135
b1011 '
b1011 )
b1001 *
b1001 -
1%
#140
0%
#145
b1010 -
b1010 *
b1100 '
b1100 )
1%
#150
0%
#155
b1101 '
b1101 )
b1011 *
b1011 -
1%
#160
0%
#165
b1100 -
b1100 *
b1110 '
b1110 )
1%
#170
0%
#175
b1111 '
b1111 )
b1101 *
b1101 -
1%
#180
0%
#185
b1110 -
b1110 *
b10000 '
b10000 )
1%
#190
0%
#195
b10001 '
b10001 )
b1111 *
b1111 -
1%
#200
0%
#205
b10000 -
b10000 *
b10010 '
b10010 )
1%
#210
0%
#215
b10011 '
b10011 )
b10001 *
b10001 -
1%
#220
0%
#225
b10010 -
b10010 *
b10100 '
b10100 )
1%
#230
0%
#235
b10101 '
b10101 )
b10011 *
b10011 -
1%
#240
0%
#245
b10100 -
b10100 *
b10110 '
b10110 )
1%
#250
0%
#255
b10111 '
b10111 )
b10101 *
b10101 -
1%
#260
0%
#265
b10110 -
b10110 *
b11000 '
b11000 )
1%
#270
0%
#275
b11001 '
b11001 )
b10111 *
b10111 -
1%
#280
0%
#285
b11000 -
b11000 *
b11010 '
b11010 )
1%
#290
0%
#295
b11011 '
b11011 )
b11001 *
b11001 -
1%
#300
0%
#305
b11010 -
b11010 *
b11100 '
b11100 )
1%
#310
0%
#315
b11101 '
b11101 )
b11011 *
b11011 -
1%
#320
0%
#325
b11100 -
b11100 *
b11110 '
b11110 )
1%
#330
0%
#335
b11111 '
b11111 )
b11101 *
b11101 -
1%
#340
0%
#345
b11110 -
b11110 *
b100000 '
b100000 )
1%
#350
0%
#355
b100001 '
b100001 )
b11111 *
b11111 -
1%
#360
0%
#365
b100000 -
b100000 *
b100010 '
b100010 )
1%
#370
0%
#375
b100011 '
b100011 )
b100001 *
b100001 -
1%
#380
0%
#385
b100010 -
b100010 *
b100100 '
b100100 )
1%
#390
0%
#395
b100101 '
b100101 )
b100011 *
b100011 -
1%
#400
0%
#405
b100100 -
b100100 *
b100110 '
b100110 )
1%
#410
0%
#415
b100111 '
b100111 )
b100101 *
b100101 -
1%
#420
0%
#425
b100110 -
b100110 *
b101000 '
b101000 )
1%
#430
0%
#435
b101001 '
b101001 )
b100111 *
b100111 -
1%
#440
0%
#445
b101000 -
b101000 *
b101010 '
b101010 )
1%
#450
0%
#455
b101011 '
b101011 )
b101001 *
b101001 -
1%
#460
0%
#465
b101010 -
b101010 *
b101100 '
b101100 )
1%
#470
0%
#475
b101101 '
b101101 )
b101011 *
b101011 -
1%
#480
0%
#485
b101100 -
b101100 *
b101110 '
b101110 )
1%
#490
0%
#495
b101111 '
b101111 )
b101101 *
b101101 -
1%
#500
0%
#505
b101110 -
b101110 *
b110000 '
b110000 )
1%
#510
0%
#515
b110001 '
b110001 )
b101111 *
b101111 -
1%
#520
0%
#525
b110000 -
b110000 *
b110010 '
b110010 )
1%
#530
0%
#535
b110011 '
b110011 )
b110001 *
b110001 -
1%
#540
0%
#545
b110010 -
b110010 *
b110100 '
b110100 )
1%
#550
0%
#555
b110101 '
b110101 )
b110011 *
b110011 -
1%
#560
0%
#565
b110100 -
b110100 *
b110110 '
b110110 )
1%
#570
0%
#575
b110111 '
b110111 )
b110101 *
b110101 -
1%
#580
0%
#585
b110110 -
b110110 *
b111000 '
b111000 )
1%
#590
0%
#595
b111001 '
b111001 )
b110111 *
b110111 -
1%
#600
0%
#605
b111000 -
b111000 *
b111010 '
b111010 )
1%
#610
0%
#615
b111011 '
b111011 )
b111001 *
b111001 -
1%
#620
0%
#625
b111010 -
b111010 *
b111100 '
b111100 )
1%
#630
0%
#635
b111101 '
b111101 )
b111011 *
b111011 -
1%
#640
0%
#645
b111100 -
b111100 *
b111110 '
b111110 )
1%
#650
0%
#655
b111111 '
b111111 )
b111101 *
b111101 -
1%
#660
0%
#665
b111110 -
b111110 *
b1000000 '
b1000000 )
1%
#670
0%
#675
b1000001 '
b1000001 )
b111111 *
b111111 -
1%
#680
0%
#685
b1000000 -
b1000000 *
b1000010 '
b1000010 )
1%
#690
0%
#695
b1000011 '
b1000011 )
b1000001 *
b1000001 -
1%
#700
0%
#705
b1000010 -
b1000010 *
b1000100 '
b1000100 )
1%
#710
0%
#715
b1000101 '
b1000101 )
b1000011 *
b1000011 -
1%
#720
0%
#725
b1000100 -
b1000100 *
b1000110 '
b1000110 )
1%
#730
0%
#735
b1000111 '
b1000111 )
b1000101 *
b1000101 -
1%
#740
0%
#745
b1000110 -
b1000110 *
b1001000 '
b1001000 )
1%
#750
0%
#755
b1001001 '
b1001001 )
b1000111 *
b1000111 -
1%
#760
0%
#765
b1001000 -
b1001000 *
b1001010 '
b1001010 )
1%
#770
0%
#775
b1001011 '
b1001011 )
b1001001 *
b1001001 -
1%
#780
0%
#785
b1001010 -
b1001010 *
b1001100 '
b1001100 )
1%
#790
0%
#795
b1001101 '
b1001101 )
b1001011 *
b1001011 -
1%
#800
0%
#805
b1001100 -
b1001100 *
b1001110 '
b1001110 )
1%
#810
0%
#815
b1001111 '
b1001111 )
b1001101 *
b1001101 -
1%
#820
0%
#825
b1001110 -
b1001110 *
b1010000 '
b1010000 )
1%
#830
0%
#835
b1010001 '
b1010001 )
b1001111 *
b1001111 -
1%
#840
0%
#845
b1010000 -
b1010000 *
b1010010 '
b1010010 )
1%
#850
0%
#855
b1010011 '
b1010011 )
b1010001 *
b1010001 -
1%
#860
0%
#865
b1010010 -
b1010010 *
b1010100 '
b1010100 )
1%
#870
0%
#875
b1010101 '
b1010101 )
b1010011 *
b1010011 -
1%
#880
0%
#885
b1010100 -
b1010100 *
b1010110 '
b1010110 )
1%
#890
0%
#895
b1010111 '
b1010111 )
b1010101 *
b1010101 -
1%
#900
0%
#905
b1010110 -
b1010110 *
b1011000 '
b1011000 )
1%
#910
0%
#915
b1011001 '
b1011001 )
b1010111 *
b1010111 -
1%
#920
0%
#925
b1011000 -
b1011000 *
b1011010 '
b1011010 )
1%
#930
0%
#935
b1011011 '
b1011011 )
b1011001 *
b1011001 -
1%
#940
0%
#945
b1011010 -
b1011010 *
b1011100 '
b1011100 )
1%
#950
0%
#955
b1011101 '
b1011101 )
b1011011 *
b1011011 -
1%
#960
0%
#965
b1011100 -
b1011100 *
b1011110 '
b1011110 )
1%
#970
0%
#975
b1011111 '
b1011111 )
b1011101 *
b1011101 -
1%
#980
0%
#985
b1011110 -
b1011110 *
b1100000 '
b1100000 )
1%
#990
0%
#995
b1100001 '
b1100001 )
b1011111 *
b1011111 -
1%
#1000
0%
#1005
b1100000 -
b1100000 *
b1100010 '
b1100010 )
1%
#1010
0%
#1015
b1100011 '
b1100011 )
b1100001 *
b1100001 -
1%
#1020
0%
#1025
b1100010 -
b1100010 *
b1100100 '
b1100100 )
1%
#1030
0%
#1035
b1100101 '
b1100101 )
b1100011 *
b1100011 -
1%
#1040
0%
#1045
b1100100 -
b1100100 *
b1100110 '
b1100110 )
1%
#1050
0%
#1055
b1100111 '
b1100111 )
b1100101 *
b1100101 -
1%
#1060
0%
#1065
b1100110 -
b1100110 *
b1101000 '
b1101000 )
1%
#1070
0%
#1075
b1101001 '
b1101001 )
b1100111 *
b1100111 -
1%
#1080
0%
#1085
b1101000 -
b1101000 *
b1101010 '
b1101010 )
1%
#1090
0%
#1095
b1101011 '
b1101011 )
b1101001 *
b1101001 -
1%
#1100
0%
#1105
b1101010 -
b1101010 *
b1101100 '
b1101100 )
1%
#1110
0%
#1115
b1101101 '
b1101101 )
b1101011 *
b1101011 -
1%
#1120
0%
#1125
b1101100 -
b1101100 *
b1101110 '
b1101110 )
1%
#1130
0%
#1135
b1101111 '
b1101111 )
b1101101 *
b1101101 -
1%
#1140
0%
#1145
b1101110 -
b1101110 *
b1110000 '
b1110000 )
1%
#1150
0%
#1155
b1110001 '
b1110001 )
b1101111 *
b1101111 -
1%
#1160
0%
#1165
b1110000 -
b1110000 *
b1110010 '
b1110010 )
1%
#1170
0%
#1175
b1110011 '
b1110011 )
b1110001 *
b1110001 -
1%
#1180
0%
#1185
b1110010 -
b1110010 *
b1110100 '
b1110100 )
1%
#1190
0%
#1195
b1110101 '
b1110101 )
b1110011 *
b1110011 -
1%
#1200
0%
#1205
b1110100 -
b1110100 *
b1110110 '
b1110110 )
1%
#1210
0%
#1215
b1110111 '
b1110111 )
b1110101 *
b1110101 -
1%
#1220
0%
#1225
b1110110 -
b1110110 *
b1111000 '
b1111000 )
1%
#1230
0%
#1235
b1111001 '
b1111001 )
b1110111 *
b1110111 -
1%
#1240
0%
#1245
b1111000 -
b1111000 *
b1111010 '
b1111010 )
1%
#1250
0%
#1255
b1111011 '
b1111011 )
b1111001 *
b1111001 -
1%
#1260
0%
#1265
b1111010 -
b1111010 *
b1111100 '
b1111100 )
1%
#1270
0%
#1275
b1111101 '
b1111101 )
b1111011 *
b1111011 -
1%
#1280
0%
#1285
b1111100 -
b1111100 *
b1111110 '
b1111110 )
1%
#1290
0%
#1295
b1111111 '
b1111111 )
1"
b0 -
1%
#1300
0%
#1305
0(
b10000000 '
b10000000 )
1$
1%
#1310
0%
#1315
b10 !
b10 ,
b1111011 *
b1 +
1%
#1320
0%
#1325
b10 +
0"
b1111010 *
b11 !
b11 ,
1%
#1330
0%
#1335
b100 !
b100 ,
b1111001 *
b11 +
1%
#1340
0%
#1345
b100 +
b1111000 *
b101 !
b101 ,
1%
#1350
0%
#1355
b110 !
b110 ,
b1110111 *
b101 +
1%
#1360
0%
#1365
b110 +
b1110110 *
b111 !
b111 ,
1%
#1370
0%
#1375
b1000 !
b1000 ,
b1110101 *
b111 +
1%
#1380
0%
#1385
b1000 +
b1110100 *
b1001 !
b1001 ,
1%
#1390
0%
#1395
b1010 !
b1010 ,
b1110011 *
b1001 +
1%
#1400
0%
#1405
b1010 +
b1110010 *
b1011 !
b1011 ,
1%
#1410
0%
#1415
b1100 !
b1100 ,
b1110001 *
b1011 +
1%
#1420
0%
#1425
b1100 +
b1110000 *
b1101 !
b1101 ,
1%
#1430
0%
#1435
b1110 !
b1110 ,
b1101111 *
b1101 +
1%
#1440
0%
#1445
b1110 +
b1101110 *
b1111 !
b1111 ,
1%
#1450
0%
#1455
b10000 !
b10000 ,
b1101101 *
b1111 +
1%
#1460
0%
#1465
b10000 +
b1101100 *
b10001 !
b10001 ,
1%
#1470
0%
#1475
b10010 !
b10010 ,
b1101011 *
b10001 +
1%
#1480
0%
#1485
b10010 +
b1101010 *
b10011 !
b10011 ,
1%
#1490
0%
#1495
b10100 !
b10100 ,
b1101001 *
b10011 +
1%
#1500
0%
#1505
b10100 +
b1101000 *
b10101 !
b10101 ,
1%
#1510
0%
#1515
b10110 !
b10110 ,
b1100111 *
b10101 +
1%
#1520
0%
#1525
b10110 +
b1100110 *
b10111 !
b10111 ,
1%
#1530
0%
#1535
b11000 !
b11000 ,
b1100101 *
b10111 +
1%
#1540
0%
#1545
b11000 +
b1100100 *
b11001 !
b11001 ,
1%
#1550
0%
#1555
b11010 !
b11010 ,
b1100011 *
b11001 +
1%
#1560
0%
#1565
b11010 +
b1100010 *
b11011 !
b11011 ,
1%
#1570
0%
#1575
b11100 !
b11100 ,
b1100001 *
b11011 +
1%
#1580
0%
#1585
b11100 +
b1100000 *
b11101 !
b11101 ,
1%
#1590
0%
#1595
b11110 !
b11110 ,
b1011111 *
b11101 +
1%
#1600
0%
#1605
b11110 +
b1011110 *
b11111 !
b11111 ,
1%
#1610
0%
#1615
b100000 !
b100000 ,
b1011101 *
b11111 +
1%
#1620
0%
#1625
b100000 +
b1011100 *
b100001 !
b100001 ,
1%
#1630
0%
#1635
b100010 !
b100010 ,
b1011011 *
b100001 +
1%
#1640
0%
#1645
b100010 +
b1011010 *
b100011 !
b100011 ,
1%
#1650
0%
#1655
b100100 !
b100100 ,
b1011001 *
b100011 +
1%
#1660
0%
#1665
b100100 +
b1011000 *
b100101 !
b100101 ,
1%
#1670
0%
#1675
b100110 !
b100110 ,
b1010111 *
b100101 +
1%
#1680
0%
#1685
b100110 +
b1010110 *
b100111 !
b100111 ,
1%
#1690
0%
#1695
b101000 !
b101000 ,
b1010101 *
b100111 +
1%
#1700
0%
#1705
b101000 +
b1010100 *
b101001 !
b101001 ,
1%
#1710
0%
#1715
b101010 !
b101010 ,
b1010011 *
b101001 +
1%
#1720
0%
#1725
b101010 +
b1010010 *
b101011 !
b101011 ,
1%
#1730
0%
#1735
b101100 !
b101100 ,
b1010001 *
b101011 +
1%
#1740
0%
#1745
b101100 +
b1010000 *
b101101 !
b101101 ,
1%
#1750
0%
#1755
b101110 !
b101110 ,
b1001111 *
b101101 +
1%
#1760
0%
#1765
b101110 +
b1001110 *
b101111 !
b101111 ,
1%
#1770
0%
#1775
b110000 !
b110000 ,
b1001101 *
b101111 +
1%
#1780
0%
#1785
b110000 +
b1001100 *
b110001 !
b110001 ,
1%
#1790
0%
#1795
b110010 !
b110010 ,
b1001011 *
b110001 +
1%
#1800
0%
#1805
b110010 +
b1001010 *
b110011 !
b110011 ,
1%
#1810
0%
#1815
b110100 !
b110100 ,
b1001001 *
b110011 +
1%
#1820
0%
#1825
b110100 +
b1001000 *
b110101 !
b110101 ,
1%
#1830
0%
#1835
b110110 !
b110110 ,
b1000111 *
b110101 +
1%
#1840
0%
#1845
b110110 +
b1000110 *
b110111 !
b110111 ,
1%
#1850
0%
#1855
b111000 !
b111000 ,
b1000101 *
b110111 +
1%
#1860
0%
#1865
b111000 +
b1000100 *
b111001 !
b111001 ,
1%
#1870
0%
#1875
b111010 !
b111010 ,
b1000011 *
b111001 +
1%
#1880
0%
#1885
b111010 +
b1000010 *
b111011 !
b111011 ,
1%
#1890
0%
#1895
b111100 !
b111100 ,
b1000001 *
b111011 +
1%
#1900
0%
#1905
b111100 +
b1000000 *
b111101 !
b111101 ,
1%
#1910
0%
#1915
b111110 !
b111110 ,
b111111 *
b111101 +
1%
#1920
0%
#1925
b111110 +
b111110 *
b111111 !
b111111 ,
1%
#1930
0%
#1935
b1000000 !
b1000000 ,
b111101 *
b111111 +
1%
#1940
0%
#1945
b1000000 +
b111100 *
b1000001 !
b1000001 ,
1%
#1950
0%
#1955
b1000010 !
b1000010 ,
b111011 *
b1000001 +
1%
#1960
0%
#1965
b1000010 +
b111010 *
b1000011 !
b1000011 ,
1%
#1970
0%
#1975
b1000100 !
b1000100 ,
b111001 *
b1000011 +
1%
#1980
0%
#1985
b1000100 +
b111000 *
b1000101 !
b1000101 ,
1%
#1990
0%
#1995
b1000110 !
b1000110 ,
b110111 *
b1000101 +
1%
#2000
0%
#2005
b1000110 +
b110110 *
b1000111 !
b1000111 ,
1%
#2010
0%
#2015
b1001000 !
b1001000 ,
b110101 *
b1000111 +
1%
#2020
0%
#2025
b1001000 +
b110100 *
b1001001 !
b1001001 ,
1%
#2030
0%
#2035
b1001010 !
b1001010 ,
b110011 *
b1001001 +
1%
#2040
0%
#2045
b1001010 +
b110010 *
b1001011 !
b1001011 ,
1%
#2050
0%
#2055
b1001100 !
b1001100 ,
b110001 *
b1001011 +
1%
#2060
0%
#2065
b1001100 +
b110000 *
b1001101 !
b1001101 ,
1%
#2070
0%
#2075
b1001110 !
b1001110 ,
b101111 *
b1001101 +
1%
#2080
0%
#2085
b1001110 +
b101110 *
b1001111 !
b1001111 ,
1%
#2090
0%
#2095
b1010000 !
b1010000 ,
b101101 *
b1001111 +
1%
#2100
0%
#2105
b1010000 +
b101100 *
b1010001 !
b1010001 ,
1%
#2110
0%
#2115
b1010010 !
b1010010 ,
b101011 *
b1010001 +
1%
#2120
0%
#2125
b1010010 +
b101010 *
b1010011 !
b1010011 ,
1%
#2130
0%
#2135
b1010100 !
b1010100 ,
b101001 *
b1010011 +
1%
#2140
0%
#2145
b1010100 +
b101000 *
b1010101 !
b1010101 ,
1%
#2150
0%
#2155
b1010110 !
b1010110 ,
b100111 *
b1010101 +
1%
#2160
0%
#2165
b1010110 +
b100110 *
b1010111 !
b1010111 ,
1%
#2170
0%
#2175
b1011000 !
b1011000 ,
b100101 *
b1010111 +
1%
#2180
0%
#2185
b1011000 +
b100100 *
b1011001 !
b1011001 ,
1%
#2190
0%
#2195
b1011010 !
b1011010 ,
b100011 *
b1011001 +
1%
#2200
0%
#2205
b1011010 +
b100010 *
b1011011 !
b1011011 ,
1%
#2210
0%
#2215
b1011100 !
b1011100 ,
b100001 *
b1011011 +
1%
#2220
0%
#2225
b1011100 +
b100000 *
b1011101 !
b1011101 ,
1%
#2230
0%
#2235
b1011110 !
b1011110 ,
b11111 *
b1011101 +
1%
#2240
0%
#2245
b1011110 +
b11110 *
b1011111 !
b1011111 ,
1%
#2250
0%
#2255
b1100000 !
b1100000 ,
b11101 *
b1011111 +
1%
#2260
0%
#2265
b1100000 +
b11100 *
b1100001 !
b1100001 ,
1%
#2270
0%
#2275
b1100010 !
b1100010 ,
b11011 *
b1100001 +
1%
#2280
0%
#2285
b1100010 +
b11010 *
b1100011 !
b1100011 ,
1%
#2290
0%
#2295
b1100100 !
b1100100 ,
b11001 *
b1100011 +
1%
#2300
0%
#2305
b1100100 +
b11000 *
b1100101 !
b1100101 ,
1%
#2310
0%
#2315
b1100110 !
b1100110 ,
b10111 *
b1100101 +
1%
#2320
0%
#2325
b1100110 +
b10110 *
b1100111 !
b1100111 ,
1%
#2330
0%
#2335
b1101000 !
b1101000 ,
b10101 *
b1100111 +
1%
#2340
0%
#2345
b1101000 +
b10100 *
b1101001 !
b1101001 ,
1%
#2350
0%
#2355
b1101010 !
b1101010 ,
b10011 *
b1101001 +
1%
#2360
0%
#2365
b1101010 +
b10010 *
b1101011 !
b1101011 ,
1%
#2370
0%
#2375
b1101100 !
b1101100 ,
b10001 *
b1101011 +
1%
#2380
0%
#2385
b1101100 +
b10000 *
b1101101 !
b1101101 ,
1%
#2390
0%
#2395
b1101110 !
b1101110 ,
b1111 *
b1101101 +
1%
#2400
0%
#2405
b1101110 +
b1110 *
b1101111 !
b1101111 ,
1%
#2410
0%
#2415
b1110000 !
b1110000 ,
b1101 *
b1101111 +
1%
#2420
0%
#2425
b1110000 +
b1100 *
b1110001 !
b1110001 ,
1%
#2430
0%
#2435
b1110010 !
b1110010 ,
b1011 *
b1110001 +
1%
#2440
0%
#2445
b1110010 +
b1010 *
b1110011 !
b1110011 ,
1%
#2450
0%
#2455
b1110100 !
b1110100 ,
b1001 *
b1110011 +
1%
#2460
0%
#2465
b1110100 +
b1000 *
b1110101 !
b1110101 ,
1%
#2470
0%
#2475
b1110110 !
b1110110 ,
b111 *
b1110101 +
1%
#2480
0%
#2485
b1110110 +
b110 *
b1110111 !
b1110111 ,
1%
#2490
0%
#2495
b1111000 !
b1111000 ,
b101 *
b1110111 +
1%
#2500
0%
#2505
b1111000 +
b100 *
b1111001 !
b1111001 ,
1%
#2510
0%
#2515
b1111010 !
b1111010 ,
b11 *
b1111001 +
1%
#2520
0%
#2525
b1111010 +
b10 *
b1111011 !
b1111011 ,
1%
#2530
0%
#2535
b1111100 !
b1111100 ,
b1 *
b1111011 +
1%
#2540
0%
#2545
b1111100 +
b0 *
b1111101 !
b1111101 ,
1%
#2550
0%
#2555
b1111110 !
b1111110 ,
1#
b0 +
1%
#2560
0%
#2565
b0zzzzzzz !
b0zzzzzzz ,
1%
