user/src/display/LCD/lcd_driver.v
module lcd_driver (
    input          pclk,
    input          rst_n,
    
    input  [15:0]  lcd_id,
    input  [23:0]  pixel_data,
    output [10:0]  pixel_row,
    output [10:0]  pixel_line,
    output [10:0]  o_h_disp,
    output [10:0]  o_v_disp,

    output         lcd_clk,
    output [23:0]  lcd_rgb,
    output         lcd_hs,
    output         lcd_vs,
    output         lcd_de
);

// 4.3' 480*272
parameter  H_SYNC_4342   =  11'd41;     //行同步
parameter  H_BACK_4342   =  11'd2;      //行显示后沿
parameter  H_DISP_4342   =  11'd480;    //行有效数据
parameter  H_FRONT_4342  =  11'd2;      //行显示前沿
parameter  H_TOTAL_4342  =  11'd525;    //行扫描周期

parameter  V_SYNC_4342   =  11'd10;     //场同步
parameter  V_BACK_4342   =  11'd2;      //场显示后沿
parameter  V_DISP_4342   =  11'd272;    //场有效数据
parameter  V_FRONT_4342  =  11'd2;      //场显示前沿
parameter  V_TOTAL_4342  =  11'd286;    //场扫描周期
   
// 7' 800*480   
parameter  H_SYNC_7084   =  11'd128;    //行同步
parameter  H_BACK_7084   =  11'd88;     //行显示后沿
parameter  H_DISP_7084   =  11'd800;    //行有效数据
parameter  H_FRONT_7084  =  11'd40;     //行显示前沿
parameter  H_TOTAL_7084  =  11'd1056;   //行扫描周期
   
parameter  V_SYNC_7084   =  11'd2;      //场同步
parameter  V_BACK_7084   =  11'd33;     //场显示后沿
parameter  V_DISP_7084   =  11'd480;    //场有效数据
parameter  V_FRONT_7084  =  11'd10;     //场显示前沿
parameter  V_TOTAL_7084  =  11'd525;    //场扫描周期       
   
// 7' 1024*600   
parameter  H_SYNC_7016   =  11'd20;     //行同步
parameter  H_BACK_7016   =  11'd140;    //行显示后沿
parameter  H_DISP_7016   =  11'd1024;   //行有效数据
parameter  H_FRONT_7016  =  11'd160;    //行显示前沿
parameter  H_TOTAL_7016  =  11'd1344;   //行扫描周期
   
parameter  V_SYNC_7016   =  11'd3;      //场同步
parameter  V_BACK_7016   =  11'd20;     //场显示后沿
parameter  V_DISP_7016   =  11'd600;    //场有效数据
parameter  V_FRONT_7016  =  11'd12;     //场显示前沿
parameter  V_TOTAL_7016  =  11'd635;    //场扫描周期
   
// 10.1' 1280*800   
parameter  H_SYNC_1018   =  11'd10;     //行同步
parameter  H_BACK_1018   =  11'd80;     //行显示后沿
parameter  H_DISP_1018   =  11'd1280;   //行有效数据
parameter  H_FRONT_1018  =  11'd70;     //行显示前沿
parameter  H_TOTAL_1018  =  11'd1440;   //行扫描周期
   
parameter  V_SYNC_1018   =  11'd3;      //场同步
parameter  V_BACK_1018   =  11'd10;     //场显示后沿
parameter  V_DISP_1018   =  11'd800;    //场有效数据
parameter  V_FRONT_1018  =  11'd10;     //场显示前沿
parameter  V_TOTAL_1018  =  11'd823;    //场扫描周期

// 4.3' 800*480   
parameter  H_SYNC_4384   =  11'd128;    //行同步
parameter  H_BACK_4384   =  11'd88;     //行显示后沿
parameter  H_DISP_4384   =  11'd800;    //行有效数据
parameter  H_FRONT_4384  =  11'd40;     //行显示前沿
parameter  H_TOTAL_4384  =  11'd1056;   //行扫描周期
   
parameter  V_SYNC_4384   =  11'd2;      //场同步
parameter  V_BACK_4384   =  11'd33;     //场显示后沿
parameter  V_DISP_4384   =  11'd480;    //场有效数据
parameter  V_FRONT_4384  =  11'd10;     //场显示前沿
parameter  V_TOTAL_4384  =  11'd525;    //场扫描周期

reg [10:0] h_sync;
reg [10:0] h_back;
reg [10:0] h_disp;
reg [10:0] h_total;
reg [10:0] v_sync;
reg [10:0] v_back;
reg [10:0] v_disp;
reg [10:0] v_total;

assign o_h_disp = h_disp;
assign o_v_disp = v_disp;

//id
always @(posedge pclk) begin
    if(rst_n == 1'b0)begin
        h_sync  <= 11'd0;
        h_back  <= 11'd0;
        h_total <= 11'd0;
        v_sync  <= 11'd0;
        v_back  <= 11'd0;
        v_total <= 11'd0;
    end
    else begin
        case(lcd_id)
            16'h4342:begin
                h_sync  <= H_SYNC_4342;
                h_back  <= H_BACK_4342;
                h_disp  <= H_DISP_4342;
                h_total <= H_TOTAL_4342;
                v_sync  <= V_SYNC_4342;
                v_back  <= V_BACK_4342;
                v_disp  <= V_DISP_4342;
                v_total <= V_TOTAL_4342;
            end
            16'h7084:begin
                h_sync  <= H_SYNC_7084;
                h_back  <= H_BACK_7084;
                h_disp  <= H_DISP_7084;
                h_total <= H_TOTAL_7084;
                v_sync  <= V_SYNC_7084;
                v_back  <= V_BACK_7084;
                v_disp  <= V_DISP_7084;
                v_total <= V_TOTAL_7084;
            end
            16'h7016:begin
                h_sync  <= H_SYNC_7016;
                h_back  <= H_BACK_7016;
                h_disp  <= H_DISP_7016;
                h_total <= H_TOTAL_7016;
                v_sync  <= V_SYNC_7016;
                v_back  <= V_BACK_7016;
                v_disp  <= V_DISP_7016;
                v_total <= V_TOTAL_7016;
            end
            16'h4384:begin
                h_sync  <= H_SYNC_4384;
                h_back  <= H_BACK_4384;
                h_disp  <= H_DISP_4384;
                h_total <= H_TOTAL_4384;
                v_sync  <= V_SYNC_4384;
                v_back  <= V_BACK_4384;
                v_disp  <= V_DISP_4384;
                v_total <= V_TOTAL_4384;
            end
            16'h1018:begin
                h_sync  <= H_SYNC_1018;
                h_back  <= H_BACK_1018;
                h_disp  <= H_DISP_1018;
                h_total <= H_TOTAL_1018;
                v_sync  <= V_SYNC_1018;
                v_back  <= V_BACK_1018;
                v_disp  <= V_DISP_1018;
                v_total <= V_TOTAL_1018;
            end
            default:begin
                h_sync  <= H_SYNC_4342;
                h_back  <= H_BACK_4342;
                h_disp  <= H_DISP_4342;
                h_total <= H_TOTAL_4342;
                v_sync  <= V_SYNC_4342;
                v_back  <= V_BACK_4342;
                v_disp  <= V_DISP_4342;
                v_total <= V_TOTAL_4342;
            end
        endcase
    end
end

//cnt_row
reg [10:0] cnt_row;

always @(posedge pclk) begin
    if(rst_n == 1'b0)begin
        cnt_row <= 11'd0;
    end
    else if(cnt_row == h_total - 1'b1)begin
        cnt_row <= 11'd0;
    end
    else begin
        cnt_row <= cnt_row + 1'b1;
    end
end


//cnt_line
reg [10:0] cnt_line;

always @(posedge pclk) begin
    if(rst_n == 1'b0)begin
        cnt_line <= 11'd0;
    end
    else if((cnt_row == h_total - 1'b1) && (cnt_line == v_total - 1'b1))begin
        cnt_line <= 11'd0;
    end
    else if(cnt_row == h_total - 1'b1)begin
        cnt_line <= cnt_line + 1'b1;
    end
    else begin
        cnt_line <= cnt_line;
    end
end

//lcd_hs
reg r_lcd_hs;

assign lcd_hs = r_lcd_hs;

always @(posedge pclk) begin
    if(rst_n == 1'b0)begin
        r_lcd_hs <= 1'b0;
    end
    else if(cnt_row == h_total - 1'b1)begin
        r_lcd_hs <= 1'b1;
    end
    else if(cnt_row == h_sync - 1'b1)begin
        r_lcd_hs <= 1'b0;
    end
end

//lcd_vs
reg r_lcd_vs;

assign lcd_vs = r_lcd_vs;

always @(posedge pclk) begin
    if(rst_n == 1'b0)begin
        r_lcd_vs <= 1'b0;
    end
    else if((cnt_row == h_total - 1'b1) && (cnt_line == v_total - 1'b1))begin
        r_lcd_vs <= 1'b1;
    end
    else if((cnt_row == h_total - 1'b1) && (cnt_line == v_sync - 1'b1))begin
        r_lcd_vs <= 1'b0;
    end
end

//lcd_de
assign lcd_de  = (cnt_row  >= h_sync + h_back) && 
                 (cnt_row  <= h_sync + h_back + h_disp - 1'b1) && 
                 (cnt_line >= v_sync + v_back) &&
                 (cnt_line <= v_sync + v_back + v_disp - 1'b1);

//pixel_row and pixel_line
wire data_req;

assign data_req = (cnt_row  >= h_sync + h_back - 1'b1) && 
                  (cnt_row  <= h_sync + h_back + h_disp - 1'b1) &&
                  (cnt_line >= v_sync + v_back) &&
                  (cnt_line <= v_sync + v_back + v_disp - 1'b1);

assign pixel_row  = lcd_de ? (cnt_row  - h_sync - h_back) : 11'd0;

reg [10:0] r_pixel_line;

assign pixel_line = r_pixel_line;

always @(posedge pclk) begin
    if(rst_n == 1'b0)begin
        r_pixel_line <= 11'd0;
    end
    else if(data_req)begin
        if(pixel_row == h_disp - 1'b1)begin
            if(pixel_line == v_disp - 1'b1)begin
                r_pixel_line <= 11'd0;
            end
            else begin
                r_pixel_line <= r_pixel_line + 1'b1;
            end
        end
        else begin
            r_pixel_line <= cnt_line - v_sync - v_back;
        end
    end
    else begin
        r_pixel_line <= r_pixel_line;
    end
end

//lcd_clk
assign lcd_clk = pclk;

//lcd_rgb
assign lcd_rgb = lcd_de ? pixel_data : 24'd0;

endmodule

user/sim/LCD/driver_tb.v
module driver_tb();

parameter MAIN_FRE   = 100; //unit MHz
reg                   sys_clk = 0;
reg                   sys_rst = 0;

always begin
    #(500/MAIN_FRE) sys_clk = ~sys_clk;
end

always begin
    #50 sys_rst = 1;
end

//Instance 
// outports wire
wire [10:0] 	pixel_row;
wire [10:0] 	pixel_line;
wire        	lcd_clk;
wire [23:0] 	lcd_rgb;
wire        	lcd_hs;
wire        	lcd_vs;
wire        	lcd_de;

lcd_driver u_lcd_driver(
	.pclk       	( sys_clk     ),
	.rst_n      	( sys_rst     ),
	
    .lcd_id     	( 16'h4342    ),
	.pixel_data 	( {13'd0,pixel_row}   ),
	.pixel_row  	( pixel_row   ),
	.pixel_line 	( pixel_line  ),
	
    .lcd_clk    	( lcd_clk     ),
	.lcd_rgb    	( lcd_rgb     ),
	.lcd_hs     	( lcd_hs      ),
	.lcd_vs     	( lcd_vs      ),
	.lcd_de     	( lcd_de      )
);

endmodule  //TOP

prj/xilinx/template.sim/sim_1/behav/xsim/wave.vcd
$date
   Fri Nov 17 00:15:28 2023
$end
$version
  2018.3
$end
$timescale
  1ps
$end
$scope module driver_tb $end
$var reg 1 ! sys_clk $end
$var reg 1 " sys_rst $end
$var wire 11 # pixel_row [10:0] $end
$var wire 11 $ pixel_line [10:0] $end
$var wire 1 % lcd_clk $end
$var wire 24 & lcd_rgb [23:0] $end
$var wire 1 ' lcd_hs $end
$var wire 1 ( lcd_vs $end
$var wire 1 ) lcd_de $end
$var parameter 32 * MAIN_FRE [31:0] $end
$scope module u_lcd_driver $end
$var wire 1 + pclk $end
$var wire 1 , rst_n $end
$var wire 16 - lcd_id [15:0] $end
$var wire 24 . pixel_data [23:0] $end
$var wire 11 # pixel_row [10:0] $end
$var wire 11 $ pixel_line [10:0] $end
$var wire 11 / o_h_disp [10:0] $end
$var wire 11 0 o_v_disp [10:0] $end
$var wire 1 % lcd_clk $end
$var wire 24 & lcd_rgb [23:0] $end
$var wire 1 ' lcd_hs $end
$var wire 1 ( lcd_vs $end
$var wire 1 ) lcd_de $end
$var reg 11 1 h_sync [10:0] $end
$var reg 11 2 h_back [10:0] $end
$var reg 11 3 h_disp [10:0] $end
$var reg 11 4 h_total [10:0] $end
$var reg 11 5 v_sync [10:0] $end
$var reg 11 6 v_back [10:0] $end
$var reg 11 7 v_disp [10:0] $end
$var reg 11 8 v_total [10:0] $end
$var reg 11 9 cnt_row [10:0] $end
$var reg 11 : cnt_line [10:0] $end
$var reg 1 ; r_lcd_hs $end
$var reg 1 < r_lcd_vs $end
$var wire 1 = data_req $end
$var reg 11 > r_pixel_line [10:0] $end
$var parameter 11 ? H_SYNC_4342 [10:0] $end
$var parameter 11 @ H_BACK_4342 [10:0] $end
$var parameter 11 A H_DISP_4342 [10:0] $end
$var parameter 11 B H_FRONT_4342 [10:0] $end
$var parameter 11 C H_TOTAL_4342 [10:0] $end
$var parameter 11 D V_SYNC_4342 [10:0] $end
$var parameter 11 E V_BACK_4342 [10:0] $end
$var parameter 11 F V_DISP_4342 [10:0] $end
$var parameter 11 G V_FRONT_4342 [10:0] $end
$var parameter 11 H V_TOTAL_4342 [10:0] $end
$var parameter 11 I H_SYNC_7084 [10:0] $end
$var parameter 11 J H_BACK_7084 [10:0] $end
$var parameter 11 K H_DISP_7084 [10:0] $end
$var parameter 11 L H_FRONT_7084 [10:0] $end
$var parameter 11 M H_TOTAL_7084 [10:0] $end
$var parameter 11 N V_SYNC_7084 [10:0] $end
$var parameter 11 O V_BACK_7084 [10:0] $end
$var parameter 11 P V_DISP_7084 [10:0] $end
$var parameter 11 Q V_FRONT_7084 [10:0] $end
$var parameter 11 R V_TOTAL_7084 [10:0] $end
$var parameter 11 S H_SYNC_7016 [10:0] $end
$var parameter 11 T H_BACK_7016 [10:0] $end
$var parameter 11 U H_DISP_7016 [10:0] $end
$var parameter 11 V H_FRONT_7016 [10:0] $end
$var parameter 11 W H_TOTAL_7016 [10:0] $end
$var parameter 11 X V_SYNC_7016 [10:0] $end
$var parameter 11 Y V_BACK_7016 [10:0] $end
$var parameter 11 Z V_DISP_7016 [10:0] $end
$var parameter 11 [ V_FRONT_7016 [10:0] $end
$var parameter 11 \ V_TOTAL_7016 [10:0] $end
$var parameter 11 ] H_SYNC_1018 [10:0] $end
$var parameter 11 ^ H_BACK_1018 [10:0] $end
$var parameter 11 _ H_DISP_1018 [10:0] $end
$var parameter 11 ` H_FRONT_1018 [10:0] $end
$var parameter 11 a H_TOTAL_1018 [10:0] $end
$var parameter 11 b V_SYNC_1018 [10:0] $end
$var parameter 11 c V_BACK_1018 [10:0] $end
$var parameter 11 d V_DISP_1018 [10:0] $end
$var parameter 11 e V_FRONT_1018 [10:0] $end
$var parameter 11 f V_TOTAL_1018 [10:0] $end
$var parameter 11 g H_SYNC_4384 [10:0] $end
$var parameter 11 h H_BACK_4384 [10:0] $end
$var parameter 11 i H_DISP_4384 [10:0] $end
$var parameter 11 j H_FRONT_4384 [10:0] $end
$var parameter 11 k H_TOTAL_4384 [10:0] $end
$var parameter 11 l V_SYNC_4384 [10:0] $end
$var parameter 11 m V_BACK_4384 [10:0] $end
$var parameter 11 n V_DISP_4384 [10:0] $end
$var parameter 11 o V_FRONT_4384 [10:0] $end
$var parameter 11 p V_TOTAL_4384 [10:0] $end
$upscope $end
$upscope $end
$enddefinitions $end
#0
$dumpvars
0!
0"
bx #
bx $
0%
b0xxxxxxxxxxx &
x'
x(
x)
b1100100 *
0+
0,
b100001101000010 -
b0xxxxxxxxxxx .
bx /
bx 0
bx 1
bx 2
bx 3
bx 4
bx 5
bx 6
bx 7
bx 8
bx 9
bx :
x;
x<
x=
bx >
b101001 ?
b10 @
b111100000 A
b10 B
b1000001101 C
b1010 D
b10 E
b100010000 F
b10 G
b100011110 H
b10000000 I
b1011000 J
b1100100000 K
b101000 L
b10000100000 M
b10 N
b100001 O
b111100000 P
b1010 Q
b1000001101 R
b10100 S
b10001100 T
b10000000000 U
b10100000 V
b10101000000 W
b11 X
b10100 Y
b1001011000 Z
b1100 [
b1001111011 \
b1010 ]
b1010000 ^
b10100000000 _
b1000110 `
b10110100000 a
b11 b
b1010 c
b1100100000 d
b1010 e
b1100110111 f
b10000000 g
b1011000 h
b1100100000 i
b101000 j
b10000100000 k
b10 l
b100001 m
b111100000 n
b1010 o
b1000001101 p
$end
#5000
1!
b0 #
b0 $
1%
b0 &
0'
0(
x)
1+
b0 .
b0 1
b0 2
b0 4
b0 5
b0 6
b0 8
b0 9
b0 :
0;
0<
0=
b0 >
#10000
0!
0%
0+
#15000
1!
1%
1+
#20000
0!
0%
0+
#25000
1!
1%
1+
#30000
0!
0%
0+
#35000
1!
1%
1+
#40000
0!
0%
0+
#45000
1!
1%
1+
#50000
0!
1"
0%
0+
1,
#55000
1!
b0 #
1%
0)
1+
b111100000 /
b100010000 0
b101001 1
b10 2
b111100000 3
b1000001101 4
b1010 5
b10 6
b100010000 7
b100011110 8
b1 9
#60000
0!
0%
0+
#65000
1!
b0 #
1%
0)
1+
b10 9
#70000
0!
0%
0+
#75000
1!
b0 #
1%
0)
1+
b11 9
#80000
0!
0%
0+
#85000
1!
b0 #
1%
0)
1+
b100 9
#90000
0!
0%
0+
#95000
1!
b0 #
1%
0)
1+
b101 9
#100000
0!
0%
0+
#105000
1!
b0 #
1%
0)
1+
b110 9
#110000
0!
0%
0+
#115000
1!
b0 #
1%
0)
1+
b111 9
#120000
0!
0%
0+
#125000
1!
b0 #
1%
0)
1+
b1000 9
#130000
0!
0%
0+
#135000
1!
b0 #
1%
0)
1+
b1001 9
#140000
0!
0%
0+
#145000
1!
b0 #
1%
0)
1+
b1010 9
#150000
0!
0%
0+
#155000
1!
b0 #
1%
0)
1+
b1011 9
#160000
0!
0%
0+
#165000
1!
b0 #
1%
0)
1+
b1100 9
#170000
0!
0%
0+
#175000
1!
b0 #
1%
0)
1+
b1101 9
#180000
0!
0%
0+
#185000
1!
b0 #
1%
0)
1+
b1110 9
#190000
0!
0%
0+
#195000
1!
b0 #
1%
0)
1+
b1111 9
#200000
0!
0%
0+
#205000
1!
b0 #
1%
0)
1+
b10000 9
#210000
0!
0%
0+
#215000
1!
b0 #
1%
0)
1+
b10001 9
#220000
0!
0%
0+
#225000
1!
b0 #
1%
0)
1+
b10010 9
#230000
0!
0%
0+
#235000
1!
b0 #
1%
0)
1+
b10011 9
#240000
0!
0%
0+
#245000
1!
b0 #
1%
0)
1+
b10100 9
#250000
0!
0%
0+
#255000
1!
b0 #
1%
0)
1+
b10101 9
#260000
0!
0%
0+
#265000
1!
b0 #
1%
0)
1+
b10110 9
#270000
0!
0%
0+
#275000
1!
b0 #
1%
0)
1+
b10111 9
#280000
0!
0%
0+
#285000
1!
b0 #
1%
0)
1+
b11000 9
#290000
0!
0%
0+
#295000
1!
b0 #
1%
0)
1+
b11001 9
#300000
0!
0%
0+
#305000
1!
b0 #
1%
0)
1+
b11010 9
#310000
0!
0%
0+
#315000
1!
b0 #
1%
0)
1+
b11011 9
#320000
0!
0%
0+
#325000
1!
b0 #
1%
0)
1+
b11100 9
#330000
0!
0%
0+
#335000
1!
b0 #
1%
0)
1+
b11101 9
#340000
0!
0%
0+
#345000
1!
b0 #
1%
0)
1+
b11110 9
#350000
0!
0%
0+
#355000
1!
b0 #
1%
0)
1+
b11111 9
#360000
0!
0%
0+
#365000
1!
b0 #
1%
0)
1+
b100000 9
#370000
0!
0%
0+
#375000
1!
b0 #
1%
0)
1+
b100001 9
#380000
0!
0%
0+
#385000
1!
b0 #
1%
0)
1+
b100010 9
#390000
0!
0%
0+
#395000
1!
b0 #
1%
0)
1+
b100011 9
#400000
0!
0%
0+
#405000
1!
b0 #
1%
0)
1+
b100100 9
#410000
0!
0%
0+
#415000
1!
b0 #
1%
0)
1+
b100101 9
#420000
0!
0%
0+
#425000
1!
b0 #
1%
0)
1+
b100110 9
#430000
0!
0%
0+
#435000
1!
b0 #
1%
0)
1+
b100111 9
#440000
0!
0%
0+
#445000
1!
b0 #
1%
0)
1+
b101000 9
#450000
0!
0%
0+
#455000
1!
b0 #
1%
0)
1+
b101001 9
#460000
0!
0%
0+
#465000
1!
b0 #
1%
0)
1+
b101010 9
#470000
0!
0%
0+
#475000
1!
b0 #
1%
0)
1+
b101011 9
#480000
0!
0%
0+
#485000
1!
b0 #
1%
0)
1+
b101100 9
#490000
0!
0%
0+
#495000
1!
b0 #
1%
0)
1+
b101101 9
#500000
0!
0%
0+
#505000
1!
b0 #
1%
0)
1+
b101110 9
#510000
0!
0%
0+
#515000
1!
b0 #
1%
0)
1+
b101111 9
#520000
0!
0%
0+
#525000
1!
b0 #
1%
0)
1+
b110000 9
#530000
0!
0%
0+
#535000
1!
b0 #
1%
0)
1+
b110001 9
#540000
0!
0%
0+
#545000
1!
b0 #
1%
0)
1+
b110010 9
#550000
0!
0%
0+
#555000
1!
b0 #
1%
0)
1+
b110011 9
#560000
0!
0%
0+
#565000
1!
b0 #
1%
0)
1+
b110100 9
#570000
0!
0%
0+
#575000
1!
b0 #
1%
0)
1+
b110101 9
#580000
0!
0%
0+
#585000
1!
b0 #
1%
0)
1+
b110110 9
#590000
0!
0%
0+
#595000
1!
b0 #
1%
0)
1+
b110111 9
#600000
0!
0%
0+
#605000
1!
b0 #
1%
0)
1+
b111000 9
#610000
0!
0%
0+
#615000
1!
b0 #
1%
0)
1+
b111001 9
#620000
0!
0%
0+
#625000
1!
b0 #
1%
0)
1+
b111010 9
#630000
0!
0%
0+
#635000
1!
b0 #
1%
0)
1+
b111011 9
#640000
0!
0%
0+
#645000
1!
b0 #
1%
0)
1+
b111100 9
#650000
0!
0%
0+
#655000
1!
b0 #
1%
0)
1+
b111101 9
#660000
0!
0%
0+
#665000
1!
b0 #
1%
0)
1+
b111110 9
#670000
0!
0%
0+
#675000
1!
b0 #
1%
0)
1+
b111111 9
#680000
0!
0%
0+
#685000
1!
b0 #
1%
0)
1+
b1000000 9
#690000
0!
0%
0+
#695000
1!
b0 #
1%
0)
1+
b1000001 9
#700000
0!
0%
0+
#705000
1!
b0 #
1%
0)
1+
b1000010 9
#710000
0!
0%
0+
#715000
1!
b0 #
1%
0)
1+
b1000011 9
#720000
0!
0%
0+
#725000
1!
b0 #
1%
0)
1+
b1000100 9
#730000
0!
0%
0+
#735000
1!
b0 #
1%
0)
1+
b1000101 9
#740000
0!
0%
0+
#745000
1!
b0 #
1%
0)
1+
b1000110 9
#750000
0!
0%
0+
#755000
1!
b0 #
1%
0)
1+
b1000111 9
#760000
0!
0%
0+
#765000
1!
b0 #
1%
0)
1+
b1001000 9
#770000
0!
0%
0+
#775000
1!
b0 #
1%
0)
1+
b1001001 9
#780000
0!
0%
0+
#785000
1!
b0 #
1%
0)
1+
b1001010 9
#790000
0!
0%
0+
#795000
1!
b0 #
1%
0)
1+
b1001011 9
#800000
0!
0%
0+
#805000
1!
b0 #
1%
0)
1+
b1001100 9
#810000
0!
0%
0+
#815000
1!
b0 #
1%
0)
1+
b1001101 9
#820000
0!
0%
0+
#825000
1!
b0 #
1%
0)
1+
b1001110 9
#830000
0!
0%
0+
#835000
1!
b0 #
1%
0)
1+
b1001111 9
#840000
0!
0%
0+
#845000
1!
b0 #
1%
0)
1+
b1010000 9
#850000
0!
0%
0+
#855000
1!
b0 #
1%
0)
1+
b1010001 9
#860000
0!
0%
0+
#865000
1!
b0 #
1%
0)
1+
b1010010 9
#870000
0!
0%
0+
#875000
1!
b0 #
1%
0)
1+
b1010011 9
#880000
0!
0%
0+
#885000
1!
b0 #
1%
0)
1+
b1010100 9
#890000
0!
0%
0+
#895000
1!
b0 #
1%
0)
1+
b1010101 9
#900000
0!
0%
0+
#905000
1!
b0 #
1%
0)
1+
b1010110 9
#910000
0!
0%
0+
#915000
1!
b0 #
1%
0)
1+
b1010111 9
#920000
0!
0%
0+
#925000
1!
b0 #
1%
0)
1+
b1011000 9
#930000
0!
0%
0+
#935000
1!
b0 #
1%
0)
1+
b1011001 9
#940000
0!
0%
0+
#945000
1!
b0 #
1%
0)
1+
b1011010 9
#950000
0!
0%
0+
#955000
1!
b0 #
1%
0)
1+
b1011011 9
#960000
0!
0%
0+
#965000
1!
b0 #
1%
0)
1+
b1011100 9
#970000
0!
0%
0+
#975000
1!
b0 #
1%
0)
1+
b1011101 9
#980000
0!
0%
0+
#985000
1!
b0 #
1%
0)
1+
b1011110 9
#990000
0!
0%
0+
#995000
1!
b0 #
1%
0)
1+
b1011111 9
#1000000
0!
0%
0+
#1005000
1!
b0 #
1%
0)
1+
b1100000 9
#1010000
0!
0%
0+
#1015000
1!
b0 #
1%
0)
1+
b1100001 9
#1020000
0!
0%
0+
#1025000
1!
b0 #
1%
0)
1+
b1100010 9
#1030000
0!
0%
0+
#1035000
1!
b0 #
1%
0)
1+
b1100011 9
#1040000
0!
0%
0+
#1045000
1!
b0 #
1%
0)
1+
b1100100 9
#1050000
0!
0%
0+
#1055000
1!
b0 #
1%
0)
1+
b1100101 9
#1060000
0!
0%
0+
#1065000
1!
b0 #
1%
0)
1+
b1100110 9
#1070000
0!
0%
0+
#1075000
1!
b0 #
1%
0)
1+
b1100111 9
#1080000
0!
0%
0+
#1085000
1!
b0 #
1%
0)
1+
b1101000 9
#1090000
0!
0%
0+
#1095000
1!
b0 #
1%
0)
1+
b1101001 9
#1100000
0!
0%
0+
#1105000
1!
b0 #
1%
0)
1+
b1101010 9
#1110000
0!
0%
0+
#1115000
1!
b0 #
1%
0)
1+
b1101011 9
#1120000
0!
0%
0+
#1125000
1!
b0 #
1%
0)
1+
b1101100 9
#1130000
0!
0%
0+
#1135000
1!
b0 #
1%
0)
1+
b1101101 9
#1140000
0!
0%
0+
#1145000
1!
b0 #
1%
0)
1+
b1101110 9
#1150000
0!
0%
0+
#1155000
1!
b0 #
1%
0)
1+
b1101111 9
#1160000
0!
0%
0+
#1165000
1!
b0 #
1%
0)
1+
b1110000 9
#1170000
0!
0%
0+
#1175000
1!
b0 #
1%
0)
1+
b1110001 9
#1180000
0!
0%
0+
#1185000
1!
b0 #
1%
0)
1+
b1110010 9
#1190000
0!
0%
0+
#1195000
1!
b0 #
1%
0)
1+
b1110011 9
#1200000
0!
0%
0+
#1205000
1!
b0 #
1%
0)
1+
b1110100 9
#1210000
0!
0%
0+
#1215000
1!
b0 #
1%
0)
1+
b1110101 9
#1220000
0!
0%
0+
#1225000
1!
b0 #
1%
0)
1+
b1110110 9
#1230000
0!
0%
0+
#1235000
1!
b0 #
1%
0)
1+
b1110111 9
#1240000
0!
0%
0+
#1245000
1!
b0 #
1%
0)
1+
b1111000 9
#1250000
0!
0%
0+
#1255000
1!
b0 #
1%
0)
1+
b1111001 9
#1260000
0!
0%
0+
#1265000
1!
b0 #
1%
0)
1+
b1111010 9
#1270000
0!
0%
0+
#1275000
1!
b0 #
1%
0)
1+
b1111011 9
#1280000
0!
0%
0+
#1285000
1!
b0 #
1%
0)
1+
b1111100 9
#1290000
0!
0%
0+
#1295000
1!
b0 #
1%
0)
1+
b1111101 9
#1300000
0!
0%
0+
#1305000
1!
b0 #
1%
0)
1+
b1111110 9
#1310000
0!
0%
0+
#1315000
1!
b0 #
1%
0)
1+
b1111111 9
#1320000
0!
0%
0+
#1325000
1!
b0 #
1%
0)
1+
b10000000 9
#1330000
0!
0%
0+
#1335000
1!
b0 #
1%
0)
1+
b10000001 9
#1340000
0!
0%
0+
#1345000
1!
b0 #
1%
0)
1+
b10000010 9
#1350000
0!
0%
0+
#1355000
1!
b0 #
1%
0)
1+
b10000011 9
#1360000
0!
0%
0+
#1365000
1!
b0 #
1%
0)
1+
b10000100 9
#1370000
0!
0%
0+
#1375000
1!
b0 #
1%
0)
1+
b10000101 9
#1380000
0!
0%
0+
#1385000
1!
b0 #
1%
0)
1+
b10000110 9
#1390000
0!
0%
0+
#1395000
1!
b0 #
1%
0)
1+
b10000111 9
#1400000
0!
0%
0+
#1405000
1!
b0 #
1%
0)
1+
b10001000 9
#1410000
0!
0%
0+
#1415000
1!
b0 #
1%
0)
1+
b10001001 9
#1420000
0!
0%
0+
#1425000
1!
b0 #
1%
0)
1+
b10001010 9
#1430000
0!
0%
0+
#1435000
1!
b0 #
1%
0)
1+
b10001011 9
#1440000
0!
0%
0+
#1445000
1!
b0 #
1%
0)
1+
b10001100 9
#1450000
0!
0%
0+
#1455000
1!
b0 #
1%
0)
1+
b10001101 9
#1460000
0!
0%
0+
#1465000
1!
b0 #
1%
0)
1+
b10001110 9
#1470000
0!
0%
0+
#1475000
1!
b0 #
1%
0)
1+
b10001111 9
#1480000
0!
0%
0+
#1485000
1!
b0 #
1%
0)
1+
b10010000 9
#1490000
0!
0%
0+
#1495000
1!
b0 #
1%
0)
1+
b10010001 9
#1500000
0!
0%
0+
#1505000
1!
b0 #
1%
0)
1+
b10010010 9
#1510000
0!
0%
0+
#1515000
1!
b0 #
1%
0)
1+
b10010011 9
#1520000
0!
0%
0+
#1525000
1!
b0 #
1%
0)
1+
b10010100 9
#1530000
0!
0%
0+
#1535000
1!
b0 #
1%
0)
1+
b10010101 9
#1540000
0!
0%
0+
#1545000
1!
b0 #
1%
0)
1+
b10010110 9
#1550000
0!
0%
0+
#1555000
1!
b0 #
1%
0)
1+
b10010111 9
#1560000
0!
0%
0+
#1565000
1!
b0 #
1%
0)
1+
b10011000 9
#1570000
0!
0%
0+
#1575000
1!
b0 #
1%
0)
1+
b10011001 9
#1580000
0!
0%
0+
#1585000
1!
b0 #
1%
0)
1+
b10011010 9
#1590000
0!
0%
0+
#1595000
1!
b0 #
1%
0)
1+
b10011011 9
#1600000
0!
0%
0+
#1605000
1!
b0 #
1%
0)
1+
b10011100 9
#1610000
0!
0%
0+
#1615000
1!
b0 #
1%
0)
1+
b10011101 9
#1620000
0!
0%
0+
#1625000
1!
b0 #
1%
0)
1+
b10011110 9
#1630000
0!
0%
0+
#1635000
1!
b0 #
1%
0)
1+
b10011111 9
#1640000
0!
0%
0+
#1645000
1!
b0 #
1%
0)
1+
b10100000 9
#1650000
0!
0%
0+
#1655000
1!
b0 #
1%
0)
1+
b10100001 9
#1660000
0!
0%
0+
#1665000
1!
b0 #
1%
0)
1+
b10100010 9
#1670000
0!
0%
0+
#1675000
1!
b0 #
1%
0)
1+
b10100011 9
#1680000
0!
0%
0+
#1685000
1!
b0 #
1%
0)
1+
b10100100 9
#1690000
0!
0%
0+
#1695000
1!
b0 #
1%
0)
1+
b10100101 9
#1700000
0!
0%
0+
#1705000
1!
b0 #
1%
0)
1+
b10100110 9
#1710000
0!
0%
0+
#1715000
1!
b0 #
1%
0)
1+
b10100111 9
#1720000
0!
0%
0+
#1725000
1!
b0 #
1%
0)
1+
b10101000 9
#1730000
0!
0%
0+
#1735000
1!
b0 #
1%
0)
1+
b10101001 9
#1740000
0!
0%
0+
#1745000
1!
b0 #
1%
0)
1+
b10101010 9
#1750000
0!
0%
0+
#1755000
1!
b0 #
1%
0)
1+
b10101011 9
#1760000
0!
0%
0+
#1765000
1!
b0 #
1%
0)
1+
b10101100 9
#1770000
0!
0%
0+
#1775000
1!
b0 #
1%
0)
1+
b10101101 9
#1780000
0!
0%
0+
